Workbook

Sheet Sheet1
AQ2: deal_stage | AR2: Won | AU2: deal_stage | AV2: Won
A3: Row Labels | B3: Count of opportunity_id | D3: Row Labels | E3: Count of opportunity_id | F3: Count of close_date | G3: Count of engage_date | H3: Count of close_value | J3: Row Labels | K3: Count of opportunity_id | L3: Min of engage_date | M3: Max of engage_date | N3: Min of close_date | O3: Max of close_date | Q3: Row Labels | R3: Count of opportunity_id | S3: Sum of close_value | V3: Column Labels
A4: Engaging | B4: 1589 | D4: Engaging | E4: 1589 | G4: 1589 | J4: Engaging | K4: 1589 | L4: 42677 | M4: 43091 | Q4: Engaging | R4: 1589 | V4: Sum of won flag | Z4: Count of opportunity_id | AD4: Sum of close_value | AH4: Sum of lost flag | AL4: Total Sum of won flag | AM4: Total Count of opportunity_id | AN4: Total Sum of close_value | AO4: Total Sum of lost flag | AR4: Sum of close_value | AU4: Row Labels | AV4: Sum of close_value
A5: Lost | B5: 2473 | D5: Lost | E5: 2473 | F5: 2473 | G5: 2473 | H5: 2473 | J5: Lost | K5: 2473 | L5: 42678 | M5: 43091 | N5: 42795 | O5: 43100 | Q5: Lost | R5: 2473 | S5: 0 | U5: Row Labels | V5: Engaging | W5: Lost | X5: Prospecting | Y5: Won | Z5: Engaging | AA5: Lost | AB5: Prospecting | AC5: Won | AD5: Engaging | AE5: Lost | AF5: Prospecting | AG5: Won | AH5: Engaging | AI5: Lost | AJ5: Prospecting | AK5: Won | AQ5: GTK 500 | AR5: 400612 | AU5: Darcel Schlecht | AV5: 1153214
A6: Prospecting | B6: 500 | D6: Prospecting | E6: 500 | J6: Prospecting | K6: 500 | Q6: Prospecting | R6: 500 | U6: Anna Snelling | V6: 0 | W6: 0 | X6: 0 | Y6: 208 | Z6: 57 | AA6: 128 | AB6: 55 | AC6: 208 | AE6: 0 | AG6: 275056 | AH6: 0 | AI6: 128 | AJ6: 0 | AK6: 0 | AL6: 208 | AM6: 448 | AN6: 275056 | AO6: 128 | AQ6: GTX Basic | AR6: 499263 | AU6: Vicki Laflamme | AV6: 478396
A7: Won | B7: 4238 | D7: Won | E7: 4238 | F7: 4238 | G7: 4238 | H7: 4238 | J7: Won | K7: 4238 | L7: 42663 | M7: 43096 | N7: 42795 | O7: 43100 | Q7: Won | R7: 4238 | S7: 10005534 | U7: Boris Faz | V7: 0 | W7: 0 | Y7: 101 | Z7: 57 | AA7: 52 | AC7: 101 | AE7: 0 | AG7: 261631 | AH7: 0 | AI7: 52 | AK7: 0 | AL7: 101 | AM7: 210 | AN7: 261631 | AO7: 52 | AQ7: GTX Plus Basic | AR7: 705275 | AU7: Kary Hendrixson | AV7: 454298
A8: Grand Total | B8: 8800 | D8: Grand Total | E8: 8800 | F8: 6711 | G8: 8300 | H8: 6711 | J8: Grand Total | K8: 8800 | L8: 42663 | M8: 43096 | N8: 42795 | O8: 43100 | Q8: Grand Total | R8: 8800 | S8: 10005534 | U8: Cassey Cress | V8: 0 | W8: 0 | Y8: 163 | Z8: 85 | AA8: 98 | AC8: 163 | AE8: 0 | AG8: 450489 | AH8: 0 | AI8: 98 | AK8: 0 | AL8: 163 | AM8: 346 | AN8: 450489 | AO8: 98 | AQ8: GTX Plus Pro | AR8: 2629651 | AU8: Cassey Cress | AV8: 450489
U9: Cecily Lampkin | V9: 0 | W9: 0 | X9: 0 | Y9: 107 | Z9: 19 | AA9: 53 | AB9: 24 | AC9: 107 | AE9: 0 | AG9: 229800 | AH9: 0 | AI9: 53 | AJ9: 0 | AK9: 0 | AL9: 107 | AM9: 203 | AN9: 229800 | AO9: 53 | AQ9: GTXPro | AR9: 3510578 | AU9: Donn Cantrell | AV9: 445860
U10: Corliss Cosme | V10: 0 | W10: 0 | Y10: 150 | Z10: 81 | AA10: 79 | AC10: 150 | AE10: 0 | AG10: 421036 | AH10: 0 | AI10: 79 | AK10: 0 | AL10: 150 | AM10: 310 | AN10: 421036 | AO10: 79 | AQ10: MG Advanced | AR10: 2216387 | AU10: Reed Clapper | AV10: 438336
D11: Row Labels | E11: Count of opportunity_id | J11: Row Labels | K11: Count of opportunity_id | U11: Daniell Hammack | V11: 0 | W11: 0 | Y11: 114 | Z11: 72 | AA11: 73 | AC11: 114 | AE11: 0 | AG11: 364229 | AH11: 0 | AI11: 73 | AK11: 0 | AL11: 114 | AM11: 259 | AN11: 364229 | AO11: 73 | AQ11: MG Special | AR11: 43768 | AU11: Zane Levy | AV11: 430068
D12: Prospecting | E12: 500 | J12: Lost | K12: 2473 | U12: Darcel Schlecht | V12: 0 | W12: 0 | X12: 0 | Y12: 349 | Z12: 83 | AA12: 204 | AB12: 111 | AC12: 349 | AE12: 0 | AG12: 1153214 | AH12: 0 | AI12: 204 | AJ12: 0 | AK12: 0 | AL12: 349 | AM12: 747 | AN12: 1153214 | AO12: 204 | AQ12: Grand Total | AR12: 10005534 | AU12: Corliss Cosme | AV12: 421036
D13: Engaging | E13: 1589 | J13: Won | K13: 4238 | U13: Donn Cantrell | W13: 0 | Y13: 158 | AA13: 117 | AC13: 158 | AE13: 0 | AG13: 445860 | AI13: 117 | AK13: 0 | AL13: 158 | AM13: 275 | AN13: 445860 | AO13: 117 | AU13: James Ascencio | AV13: 413533
D14: Lost | E14: 2473 | U14: Elease Gluck | V14: 0 | W14: 0 | Y14: 80 | Z14: 51 | AA14: 46 | AC14: 80 | AE14: 0 | AG14: 289195 | AH14: 0 | AI14: 46 | AK14: 0 | AL14: 80 | AM14: 177 | AN14: 289195 | AO14: 46 | AU14: Daniell Hammack | AV14: 364229
D15: Won | E15: 4238 | U15: Garret Kinder | W15: 0 | Y15: 75 | AA15: 48 | AC15: 75 | AE15: 0 | AG15: 197773 | AI15: 48 | AK15: 0 | AL15: 75 | AM15: 123 | AN15: 197773 | AO15: 48 | AQ15: Row Labels | AR15: Sum of close_value | AU15: Grand Total | AV15: 5049459
U16: Gladys Colclough | V16: 0 | W16: 0 | X16: 0 | Y16: 135 | Z16: 36 | AA16: 97 | AB16: 49 | AC16: 135 | AE16: 0 | AG16: 345674 | AH16: 0 | AI16: 97 | AJ16: 0 | AK16: 0 | AL16: 135 | AM16: 317 | AN16: 345674 | AO16: 97 | AQ16: GTK 500 | AR16: 400612
U17: Hayden Neloms | V17: 0 | W17: 0 | Y17: 107 | Z17: 50 | AA17: 45 | AC17: 107 | AE17: 0 | AG17: 272111 | AH17: 0 | AI17: 45 | AK17: 0 | AL17: 107 | AM17: 202 | AN17: 272111 | AO17: 45 | AQ17: GTX Basic | AR17: 499263 | AU17: Row Labels | AV17: Sum of close_value
U18: James Ascencio | V18: 0 | W18: 0 | Y18: 135 | Z18: 61 | AA18: 71 | AC18: 135 | AE18: 0 | AG18: 413533 | AH18: 0 | AI18: 71 | AK18: 0 | AL18: 135 | AM18: 267 | AN18: 413533 | AO18: 71 | AQ18: GTX Plus Basic | AR18: 705275 | AU18: Darcel Schlecht | AV18: 1153214
U19: Jonathan Berthelot | V19: 0 | W19: 0 | X19: 0 | Y19: 171 | Z19: 33 | AA19: 93 | AB19: 48 | AC19: 171 | AE19: 0 | AG19: 284886 | AH19: 0 | AI19: 93 | AJ19: 0 | AK19: 0 | AL19: 171 | AM19: 345 | AN19: 284886 | AO19: 93 | AQ19: GTX Plus Pro | AR19: 2629651 | AU19: Vicki Laflamme | AV19: 478396
U20: Kami Bicknell | V20: 0 | W20: 0 | Y20: 174 | Z20: 90 | AA20: 98 | AC20: 174 | AE20: 0 | AG20: 316456 | AH20: 0 | AI20: 98 | AK20: 0 | AL20: 174 | AM20: 362 | AN20: 316456 | AO20: 98 | AQ20: GTXPro | AR20: 3510578 | AU20: Kary Hendrixson | AV20: 454298
U21: Kary Hendrixson | V21: 0 | W21: 0 | Y21: 209 | Z21: 103 | AA21: 126 | AC21: 209 | AE21: 0 | AG21: 454298 | AH21: 0 | AI21: 126 | AK21: 0 | AL21: 209 | AM21: 438 | AN21: 454298 | AO21: 126 | AQ21: MG Advanced | AR21: 2216387 | AU21: Cassey Cress | AV21: 450489
U22: Lajuana Vencill | V22: 0 | W22: 0 | X22: 0 | Y22: 127 | Z22: 40 | AA22: 104 | AB22: 40 | AC22: 127 | AE22: 0 | AG22: 194632 | AH22: 0 | AI22: 104 | AJ22: 0 | AK22: 0 | AL22: 127 | AM22: 311 | AN22: 194632 | AO22: 104 | AQ22: MG Special | AR22: 43768 | AU22: Donn Cantrell | AV22: 445860
U23: Markita Hansen | V23: 0 | W23: 0 | Y23: 130 | Z23: 79 | AA23: 97 | AC23: 130 | AE23: 0 | AG23: 328792 | AH23: 0 | AI23: 97 | AK23: 0 | AL23: 130 | AM23: 306 | AN23: 328792 | AO23: 97 | AU23: Reed Clapper | AV23: 438336
U24: Marty Freudenburg | V24: 0 | W24: 0 | X24: 0 | Y24: 122 | Z24: 33 | AA24: 72 | AB24: 54 | AC24: 122 | AE24: 0 | AG24: 291195 | AH24: 0 | AI24: 72 | AJ24: 0 | AK24: 0 | AL24: 122 | AM24: 281 | AN24: 291195 | AO24: 72 | AU24: Zane Levy | AV24: 430068
U25: Maureen Marcano | V25: 0 | W25: 0 | Y25: 149 | Z25: 72 | AA25: 64 | AC25: 149 | AE25: 0 | AG25: 350395 | AH25: 0 | AI25: 64 | AK25: 0 | AL25: 149 | AM25: 285 | AN25: 350395 | AO25: 64 | AU25: Corliss Cosme | AV25: 421036
U26: Moses Frase | V26: 0 | W26: 0 | X26: 0 | Y26: 129 | Z26: 34 | AA26: 66 | AB26: 31 | AC26: 129 | AE26: 0 | AG26: 207182 | AH26: 0 | AI26: 66 | AJ26: 0 | AK26: 0 | AL26: 129 | AM26: 260 | AN26: 207182 | AO26: 66 | AU26: James Ascencio | AV26: 413533
U27: Niesha Huffines | V27: 0 | W27: 0 | X27: 0 | Y27: 105 | Z27: 30 | AA27: 70 | AB27: 34 | AC27: 105 | AE27: 0 | AG27: 176961 | AH27: 0 | AI27: 70 | AJ27: 0 | AK27: 0 | AL27: 105 | AM27: 239 | AN27: 176961 | AO27: 70 | AU27: Daniell Hammack | AV27: 364229
U28: Reed Clapper | W28: 0 | Y28: 155 | AA28: 82 | AC28: 155 | AE28: 0 | AG28: 438336 | AI28: 82 | AK28: 0 | AL28: 155 | AM28: 237 | AN28: 438336 | AO28: 82
U29: Rosalina Dieter | V29: 0 | W29: 0 | Y29: 72 | Z29: 50 | AA29: 38 | AC29: 72 | AE29: 0 | AG29: 235403 | AH29: 0 | AI29: 38 | AK29: 0 | AL29: 72 | AM29: 160 | AN29: 235403 | AO29: 38
U30: Rosie Papadopoulos | V30: 0 | W30: 0 | Y30: 78 | Z30: 39 | AA30: 43 | AC30: 78 | AE30: 0 | AG30: 230169 | AH30: 0 | AI30: 43 | AK30: 0 | AL30: 78 | AM30: 160 | AN30: 230169 | AO30: 43
U31: Versie Hillebrand | V31: 0 | W31: 0 | X31: 0 | Y31: 176 | Z31: 43 | AA31: 88 | AB31: 54 | AC31: 176 | AE31: 0 | AG31: 187693 | AH31: 0 | AI31: 88 | AJ31: 0 | AK31: 0 | AL31: 176 | AM31: 361 | AN31: 187693 | AO31: 88
U32: Vicki Laflamme | V32: 0 | W32: 0 | Y32: 221 | Z32: 104 | AA32: 126 | AC32: 221 | AE32: 0 | AG32: 478396 | AH32: 0 | AI32: 126 | AK32: 0 | AL32: 221 | AM32: 451 | AN32: 478396 | AO32: 126
U33: Violet Mclelland | V33: 0 | W33: 0 | Y33: 122 | Z33: 68 | AA33: 71 | AC33: 122 | AE33: 0 | AG33: 123431 | AH33: 0 | AI33: 71 | AK33: 0 | AL33: 122 | AM33: 261 | AN33: 123431 | AO33: 71
U34: Wilburn Farren | V34: 0 | W34: 0 | Y34: 55 | Z34: 31 | AA34: 24 | AC34: 55 | AE34: 0 | AG34: 157640 | AH34: 0 | AI34: 24 | AK34: 0 | AL34: 55 | AM34: 110 | AN34: 157640 | AO34: 24
U35: Zane Levy | V35: 0 | W35: 0 | Y35: 161 | Z35: 88 | AA35: 100 | AC35: 161 | AE35: 0 | AG35: 430068 | AH35: 0 | AI35: 100 | AK35: 0 | AL35: 161 | AM35: 349 | AN35: 430068 | AO35: 100
U36: Grand Total | V36: 0 | W36: 0 | X36: 0 | Y36: 4238 | Z36: 1589 | AA36: 2473 | AB36: 500 | AC36: 4238 | AE36: 0 | AG36: 10005534 | AH36: 0 | AI36: 2473 | AJ36: 0 | AK36: 0 | AL36: 4238 | AM36: 8800 | AN36: 10005534 | AO36: 2473
U39: =IFERROR(Won/(Won+lost),0) -> 0

Sheet Dashboard

Sheet Sheet3
A1: deal_stage | B1: Won
D2: deal_stage | E2: Won
A3: Row Labels | B3: Sum of close_value
A4: retail | B4: 1867528 | D4: Row Labels | E4: Sum of close_value
A5: technolgy | B5: 1515487 | D5: West | E5: 3568647
A6: medical | B6: 1359595 | D6: Central | E6: 3346293
A7: software | B7: 1077934 | D7: East | E7: 3090594
A8: finance | B8: 950908 | D8: Grand Total | E8: 10005534
A9: Grand Total | B9: 6771452

Sheet sales_pipeline
A1: opportunity_id | B1: sales_agent | C1: manager | D1: sector | E1: account cleaned | F1: regional office | G1: office location | H1: product | I1: account | J1: account revenue | K1: employee count | L1: deal_stage | M1: engage_date | N1: close_date | O1: close_value | P1: date check | Q1: won flag | R1: lost flag
A2: 1C1I7A6R | B2: Moses Frase | C2: =VLOOKUP(Table1[[#This Row],[sales_agent]],'sales team'!A:C,2,FALSE) -> Dustin Brinkmann | D2: =IF(E2="","No account",IFERROR(INDEX(account!$B:$B,MATCH(TRIM(CLEAN(E2)),account!$A:$A,0)),"Not Found")) -> retail | E2: =TRIM(CLEAN(I2)) -> Cancity | F2: =VLOOKUP(Table1[[#This Row],[sales_agent]],'sales team'!A:C,3,FALSE) -> Central | G2: =IF(E2="","No account",IFERROR(INDEX(account!$F:$F,MATCH(TRIM(CLEAN(E2)),account!$A:$A,0)),"Not Found")) -> United States | H2: GTX Plus Basic | I2: Cancity | J2: =IF(E2="","No account",IFERROR(INDEX(account!$D:$D,MATCH(TRIM(CLEAN(E2)),account!$A:$A,0)),"Not Found")) -> 718.62 | K2: =IF(E2="","No account",IFERROR(INDEX(account!$E:$E,MATCH(TRIM(CLEAN(E2)),account!$A:$A,0)),"Not Found")) -> 2448 | L2: Won | M2: 42663 | N2: 42795 | O2: 1054 | P2: =IF(OR(M2="",N2=""),"N/A",IF(N2<M2,"ERROR","OK")) -> OK | Q2: =IF(Table1[[#This Row],[deal_stage]]="Won",1,0) -> 1 | R2: =IF(Table1[[#This Row],[deal_stage]] ="Lost",1,0) -> 0
A3: Z063OYW0 | B3: Darcel Schlecht | C3: =VLOOKUP(Table1[[#This Row],[sales_agent]],'sales team'!A:C,2,FALSE) -> Melvin Marxen | D3: =IF(E3="","No account",IFERROR(INDEX(account!$B:$B,MATCH(TRIM(CLEAN(E3)),account!$A:$A,0)),"Not Found")) -> medical | E3: =TRIM(CLEAN(I3)) -> Isdom | F3: =VLOOKUP(Table1[[#This Row],[sales_agent]],'sales team'!A:C,3,FALSE) -> Central | G3: =IF(E3="","No account",IFERROR(INDEX(account!$F:$F,MATCH(TRIM(CLEAN(E3)),account!$A:$A,0)),"Not Found")) -> United States | H3: GTXPro | I3: Isdom | J3: =IF(E3="","No account",IFERROR(INDEX(account!$D:$D,MATCH(TRIM(CLEAN(E3)),account!$A:$A,0)),"Not Found")) -> 3178.24 | K3: =IF(E3="","No account",IFERROR(INDEX(account!$E:$E,MATCH(TRIM(CLEAN(E3)),account!$A:$A,0)),"Not Found")) -> 4540 | L3: Won | M3: 42668 | N3: 42805 | O3: 4514 | P3: =IF(OR(M3="",N3=""),"N/A",IF(N3<M3,"ERROR","OK")) -> OK | Q3: =IF(Table1[[#This Row],[deal_stage]]="Won",1,0) -> 1 | R3: =IF(Table1[[#This Row],[deal_stage]] ="Lost",1,0) -> 0
A4: EC4QE1BX | B4: Darcel Schlecht | C4: =VLOOKUP(Table1[[#This Row],[sales_agent]],'sales team'!A:C,2,FALSE) -> Melvin Marxen | D4: =IF(E4="","No account",IFERROR(INDEX(account!$B:$B,MATCH(TRIM(CLEAN(E4)),account!$A:$A,0)),"Not Found")) -> retail | E4: =TRIM(CLEAN(I4)) -> Cancity | F4: =VLOOKUP(Table1[[#This Row],[sales_agent]],'sales team'!A:C,3,FALSE) -> Central | G4: =IF(E4="","No account",IFERROR(INDEX(account!$F:$F,MATCH(TRIM(CLEAN(E4)),account!$A:$A,0)),"Not Found")) -> United States | H4: MG Special | I4: Cancity | J4: =IF(E4="","No account",IFERROR(INDEX(account!$D:$D,MATCH(TRIM(CLEAN(E4)),account!$A:$A,0)),"Not Found")) -> 718.62 | K4: =IF(E4="","No account",IFERROR(INDEX(account!$E:$E,MATCH(TRIM(CLEAN(E4)),account!$A:$A,0)),"Not Found")) -> 2448 | L4: Won | M4: 42668 | N4: 42801 | O4: 50 | P4: =IF(OR(M4="",N4=""),"N/A",IF(N4<M4,"ERROR","OK")) -> OK | Q4: =IF(Table1[[#This Row],[deal_stage]]="Won",1,0) -> 1 | R4: =IF(Table1[[#This Row],[deal_stage]] ="Lost",1,0) -> 0
A5: MV1LWRNH | B5: Moses Frase | C5: =VLOOKUP(Table1[[#This Row],[sales_agent]],'sales team'!A:C,2,FALSE) -> Dustin Brinkmann | D5: =IF(E5="","No account",IFERROR(INDEX(account!$B:$B,MATCH(TRIM(CLEAN(E5)),account!$A:$A,0)),"Not Found")) -> software | E5: =TRIM(CLEAN(I5)) -> Codehow | F5: =VLOOKUP(Table1[[#This Row],[sales_agent]],'sales team'!A:C,3,FALSE) -> Central | G5: =IF(E5="","No account",IFERROR(INDEX(account!$F:$F,MATCH(TRIM(CLEAN(E5)),account!$A:$A,0)),"Not Found")) -> United States | H5: GTX Basic | I5: Codehow | J5: =IF(E5="","No account",IFERROR(INDEX(account!$D:$D,MATCH(TRIM(CLEAN(E5)),account!$A:$A,0)),"Not Found")) -> 2714.9 | K5: =IF(E5="","No account",IFERROR(INDEX(account!$E:$E,MATCH(TRIM(CLEAN(E5)),account!$A:$A,0)),"Not Found")) -> 2641 | L5: Won | M5: 42668 | N5: 42803 | O5: 588 | P5: =IF(OR(M5="",N5=""),"N/A",IF(N5<M5,"ERROR","OK")) -> OK | Q5: =IF(Table1[[#This Row],[deal_stage]]="Won",1,0) -> 1 | R5: =IF(Table1[[#This Row],[deal_stage]] ="Lost",1,0) -> 0
A6: PE84CX4O | B6: Zane Levy | C6: =VLOOKUP(Table1[[#This Row],[sales_agent]],'sales team'!A:C,2,FALSE) -> Summer Sewald | D6: =IF(E6="","No account",IFERROR(INDEX(account!$B:$B,MATCH(TRIM(CLEAN(E6)),account!$A:$A,0)),"Not Found")) -> services | E6: =TRIM(CLEAN(I6)) -> Hatfan | F6: =VLOOKUP(Table1[[#This Row],[sales_agent]],'sales team'!A:C,3,FALSE) -> West | G6: =IF(E6="","No account",IFERROR(INDEX(account!$F:$F,MATCH(TRIM(CLEAN(E6)),account!$A:$A,0)),"Not Found")) -> United States | H6: GTX Basic | I6: Hatfan | J6: =IF(E6="","No account",IFERROR(INDEX(account!$D:$D,MATCH(TRIM(CLEAN(E6)),account!$A:$A,0)),"Not Found")) -> 792.46 | K6: =IF(E6="","No account",IFERROR(INDEX(account!$E:$E,MATCH(TRIM(CLEAN(E6)),account!$A:$A,0)),"Not Found")) -> 1299 | L6: Won | M6: 42668 | N6: 42796 | O6: 517 | P6: =IF(OR(M6="",N6=""),"N/A",IF(N6<M6,"ERROR","OK")) -> OK | Q6: =IF(Table1[[#This Row],[deal_stage]]="Won",1,0) -> 1 | R6: =IF(Table1[[#This Row],[deal_stage]] ="Lost",1,0) -> 0
A7: ZNBS69V1 | B7: Anna Snelling | C7: =VLOOKUP(Table1[[#This Row],[sales_agent]],'sales team'!A:C,2,FALSE) -> Dustin Brinkmann | D7: =IF(E7="","No account",IFERROR(INDEX(account!$B:$B,MATCH(TRIM(CLEAN(E7)),account!$A:$A,0)),"Not Found")) -> medical | E7: =TRIM(CLEAN(I7)) -> Ron-tech | F7: =VLOOKUP(Table1[[#This Row],[sales_agent]],'sales team'!A:C,3,FALSE) -> Central | G7: =IF(E7="","No account",IFERROR(INDEX(account!$F:$F,MATCH(TRIM(CLEAN(E7)),account!$A:$A,0)),"Not Found")) -> United States | H7: MG Special | I7: Ron-tech | J7: =IF(E7="","No account",IFERROR(INDEX(account!$D:$D,MATCH(TRIM(CLEAN(E7)),account!$A:$A,0)),"Not Found")) -> 3922.42 | K7: =IF(E7="","No account",IFERROR(INDEX(account!$E:$E,MATCH(TRIM(CLEAN(E7)),account!$A:$A,0)),"Not Found")) -> 6837 | L7: Won | M7: 42672 | N7: 42795 | O7: 49 | P7: =IF(OR(M7="",N7=""),"N/A",IF(N7<M7,"ERROR","OK")) -> OK | Q7: =IF(Table1[[#This Row],[deal_stage]]="Won",1,0) -> 1 | R7: =IF(Table1[[#This Row],[deal_stage]] ="Lost",1,0) -> 0
A8: 9ME3374G | B8: Vicki Laflamme | C8: =VLOOKUP(Table1[[#This Row],[sales_agent]],'sales team'!A:C,2,FALSE) -> Celia Rouche | D8: =IF(E8="","No account",IFERROR(INDEX(account!$B:$B,MATCH(TRIM(CLEAN(E8)),account!$A:$A,0)),"Not Found")) -> retail | E8: =TRIM(CLEAN(I8)) -> J-Texon | F8: =VLOOKUP(Table1[[#This Row],[sales_agent]],'sales team'!A:C,3,FALSE) -> West | G8: =IF(E8="","No account",IFERROR(INDEX(account!$F:$F,MATCH(TRIM(CLEAN(E8)),account!$A:$A,0)),"Not Found")) -> United States | H8: MG Special | I8: J-Texon | J8: =IF(E8="","No account",IFERROR(INDEX(account!$D:$D,MATCH(TRIM(CLEAN(E8)),account!$A:$A,0)),"Not Found")) -> 1388.67 | K8: =IF(E8="","No account",IFERROR(INDEX(account!$E:$E,MATCH(TRIM(CLEAN(E8)),account!$A:$A,0)),"Not Found")) -> 3583 | L8: Won | M8: 42673 | N8: 42796 | O8: 57 | P8: =IF(OR(M8="",N8=""),"N/A",IF(N8<M8,"ERROR","OK")) -> OK | Q8: =IF(Table1[[#This Row],[deal_stage]]="Won",1,0) -> 1 | R8: =IF(Table1[[#This Row],[deal_stage]] ="Lost",1,0) -> 0
A9: 7GN8Q4LL | B9: Markita Hansen | C9: =VLOOKUP(Table1[[#This Row],[sales_agent]],'sales team'!A:C,2,FALSE) -> Celia Rouche | D9: =IF(E9="","No account",IFERROR(INDEX(account!$B:$B,MATCH(TRIM(CLEAN(E9)),account!$A:$A,0)),"Not Found")) -> entertainment | E9: =TRIM(CLEAN(I9)) -> Cheers | F9: =VLOOKUP(Table1[[#This Row],[sales_agent]],'sales team'!A:C,3,FALSE) -> West | G9: =IF(E9="","No account",IFERROR(INDEX(account!$F:$F,MATCH(TRIM(CLEAN(E9)),account!$A:$A,0)),"Not Found")) -> United States | H9: GTX Basic | I9: Cheers | J9: =IF(E9="","No account",IFERROR(INDEX(account!$D:$D,MATCH(TRIM(CLEAN(E9)),account!$A:$A,0)),"Not Found")) -> 4269.9 | K9: =IF(E9="","No account",IFERROR(INDEX(account!$E:$E,MATCH(TRIM(CLEAN(E9)),account!$A:$A,0)),"Not Found")) -> 6472 | L9: Won | M9: 42675 | N9: 42801 | O9: 601 | P9: =IF(OR(M9="",N9=""),"N/A",IF(N9<M9,"ERROR","OK")) -> OK | Q9: =IF(Table1[[#This Row],[deal_stage]]="Won",1,0) -> 1 | R9: =IF(Table1[[#This Row],[deal_stage]] ="Lost",1,0) -> 0
A10: OLK9LKZB | B10: Niesha Huffines | C10: =VLOOKUP(Table1[[#This Row],[sales_agent]],'sales team'!A:C,2,FALSE) -> Melvin Marxen | D10: =IF(E10="","No account",IFERROR(INDEX(account!$B:$B,MATCH(TRIM(CLEAN(E10)),account!$A:$A,0)),"Not Found")) -> medical | E10: =TRIM(CLEAN(I10)) -> Zumgoity | F10: =VLOOKUP(Table1[[#This Row],[sales_agent]],'sales team'!A:C,3,FALSE) -> Central | G10: =IF(E10="","No account",IFERROR(INDEX(account!$F:$F,MATCH(TRIM(CLEAN(E10)),account!$A:$A,0)),"Not Found")) -> United States | H10: GTX Plus Basic | I10: Zumgoity | J10: =IF(E10="","No account",IFERROR(INDEX(account!$D:$D,MATCH(TRIM(CLEAN(E10)),account!$A:$A,0)),"Not Found")) -> 441.08 | K10: =IF(E10="","No account",IFERROR(INDEX(account!$E:$E,MATCH(TRIM(CLEAN(E10)),account!$A:$A,0)),"Not Found")) -> 1210 | L10: Won | M10: 42675 | N10: 42797 | O10: 1026 | P10: =IF(OR(M10="",N10=""),"N/A",IF(N10<M10,"ERROR","OK")) -> OK | Q10: =IF(Table1[[#This Row],[deal_stage]]="Won",1,0) -> 1 | R10: =IF(Table1[[#This Row],[deal_stage]] ="Lost",1,0) -> 0
A11: HAXMC4IX | B11: James Ascencio | C11: =VLOOKUP(Table1[[#This Row],[sales_agent]],'sales team'!A:C,2,FALSE) -> Summer Sewald | D11: =IF(E11="","No account",IFERROR(INDEX(account!$B:$B,MATCH(TRIM(CLEAN(E11)),account!$A:$A,0)),"Not Found")) -> No account | E11: =TRIM(CLEAN(I11)) | F11: =VLOOKUP(Table1[[#This Row],[sales_agent]],'sales team'!A:C,3,FALSE) -> West | G11: =IF(E11="","No account",IFERROR(INDEX(account!$F:$F,MATCH(TRIM(CLEAN(E11)),account!$A:$A,0)),"Not Found")) -> No account | H11: MG Advanced | J11: =IF(E11="","No account",IFERROR(INDEX(account!$D:$D,MATCH(TRIM(CLEAN(E11)),account!$A:$A,0)),"Not Found")) -> No account | K11: =IF(E11="","No account",IFERROR(INDEX(account!$E:$E,MATCH(TRIM(CLEAN(E11)),account!$A:$A,0)),"Not Found")) -> No account | L11: Engaging | M11: 42677 | P11: =IF(OR(M11="",N11=""),"N/A",IF(N11<M11,"ERROR","OK")) -> N/A | Q11: =IF(Table1[[#This Row],[deal_stage]]="Won",1,0) -> 0 | R11: =IF(Table1[[#This Row],[deal_stage]] ="Lost",1,0) -> 0
A12: NL3JZH1Z | B12: Anna Snelling | C12: =VLOOKUP(Table1[[#This Row],[sales_agent]],'sales team'!A:C,2,FALSE) -> Dustin Brinkmann | D12: =IF(E12="","No account",IFERROR(INDEX(account!$B:$B,MATCH(TRIM(CLEAN(E12)),account!$A:$A,0)),"Not Found")) -> medical | E12: =TRIM(CLEAN(I12)) -> Bioholding | F12: =VLOOKUP(Table1[[#This Row],[sales_agent]],'sales team'!A:C,3,FALSE) -> Central | G12: =IF(E12="","No account",IFERROR(INDEX(account!$F:$F,MATCH(TRIM(CLEAN(E12)),account!$A:$A,0)),"Not Found")) -> Philipines | H12: MG Special | I12: Bioholding | J12: =IF(E12="","No account",IFERROR(INDEX(account!$D:$D,MATCH(TRIM(CLEAN(E12)),account!$A:$A,0)),"Not Found")) -> 587.34 | K12: =IF(E12="","No account",IFERROR(INDEX(account!$E:$E,MATCH(TRIM(CLEAN(E12)),account!$A:$A,0)),"Not Found")) -> 1356 | L12: Won | M12: 42678 | N12: 42804 | O12: 53 | P12: =IF(OR(M12="",N12=""),"N/A",IF(N12<M12,"ERROR","OK")) -> OK | Q12: =IF(Table1[[#This Row],[deal_stage]]="Won",1,0) -> 1 | R12: =IF(Table1[[#This Row],[deal_stage]] ="Lost",1,0) -> 0
A13: KWVA7VR1 | B13: Gladys Colclough | C13: =VLOOKUP(Table1[[#This Row],[sales_agent]],'sales team'!A:C,2,FALSE) -> Melvin Marxen | D13: =IF(E13="","No account",IFERROR(INDEX(account!$B:$B,MATCH(TRIM(CLEAN(E13)),account!$A:$A,0)),"Not Found")) -> retail | E13: =TRIM(CLEAN(I13)) -> Genco Pura Olive Oil Company | F13: =VLOOKUP(Table1[[#This Row],[sales_agent]],'sales team'!A:C,3,FALSE) -> Central | G13: =IF(E13="","No account",IFERROR(INDEX(account!$F:$F,MATCH(TRIM(CLEAN(E13)),account!$A:$A,0)),"Not Found")) -> Italy | H13: GTXPro | I13: Genco Pura Olive Oil Company | J13: =IF(E13="","No account",IFERROR(INDEX(account!$D:$D,MATCH(TRIM(CLEAN(E13)),account!$A:$A,0)),"Not Found")) -> 894.33 | K13: =IF(E13="","No account",IFERROR(INDEX(account!$E:$E,MATCH(TRIM(CLEAN(E13)),account!$A:$A,0)),"Not Found")) -> 1635 | L13: Lost | M13: 42678 | N13: 42812 | O13: 0 | P13: =IF(OR(M13="",N13=""),"N/A",IF(N13<M13,"ERROR","OK")) -> OK | Q13: =IF(Table1[[#This Row],[deal_stage]]="Won",1,0) -> 0 | R13: =IF(Table1[[#This Row],[deal_stage]] ="Lost",1,0) -> 1
A14: S8DX3XOU | B14: James Ascencio | C14: =VLOOKUP(Table1[[#This Row],[sales_agent]],'sales team'!A:C,2,FALSE) -> Summer Sewald | D14: =IF(E14="","No account",IFERROR(INDEX(account!$B:$B,MATCH(TRIM(CLEAN(E14)),account!$A:$A,0)),"Not Found")) -> marketing | E14: =TRIM(CLEAN(I14)) -> Sunnamplex | F14: =VLOOKUP(Table1[[#This Row],[sales_agent]],'sales team'!A:C,3,FALSE) -> West | G14: =IF(E14="","No account",IFERROR(INDEX(account!$F:$F,MATCH(TRIM(CLEAN(E14)),account!$A:$A,0)),"Not Found")) -> Poland | H14: GTX Plus Pro | I14: Sunnamplex | J14: =IF(E14="","No account",IFERROR(INDEX(account!$D:$D,MATCH(TRIM(CLEAN(E14)),account!$A:$A,0)),"Not Found")) -> 894.37 | K14: =IF(E14="","No account",IFERROR(INDEX(account!$E:$E,MATCH(TRIM(CLEAN(E14)),account!$A:$A,0)),"Not Found")) -> 1593 | L14: Won | M14: 42678 | N14: 42804 | O14: 5169 | P14: =IF(OR(M14="",N14=""),"N/A",IF(N14<M14,"ERROR","OK")) -> OK | Q14: =IF(Table1[[#This Row],[deal_stage]]="Won",1,0) -> 1 | R14: =IF(Table1[[#This Row],[deal_stage]] ="Lost",1,0) -> 0
A15: ENB2XD8G | B15: Maureen Marcano | C15: =VLOOKUP(Table1[[#This Row],[sales_agent]],'sales team'!A:C,2,FALSE) -> Summer Sewald | D15: =IF(E15="","No account",IFERROR(INDEX(account!$B:$B,MATCH(TRIM(CLEAN(E15)),account!$A:$A,0)),"Not Found")) -> telecommunications | E15: =TRIM(CLEAN(I15)) -> Sonron | F15: =VLOOKUP(Table1[[#This Row],[sales_agent]],'sales team'!A:C,3,FALSE) -> West | G15: =IF(E15="","No account",IFERROR(INDEX(account!$F:$F,MATCH(TRIM(CLEAN(E15)),account!$A:$A,0)),"Not Found")) -> United States | H15: GTX Plus Pro | I15: Sonron | J15: =IF(E15="","No account",IFERROR(INDEX(account!$D:$D,MATCH(TRIM(CLEAN(E15)),account!$A:$A,0)),"Not Found")) -> 1699.85 | K15: =IF(E15="","No account",IFERROR(INDEX(account!$E:$E,MATCH(TRIM(CLEAN(E15)),account!$A:$A,0)),"Not Found")) -> 5108 | L15: Won | M15: 42678 | N15: 42800 | O15: 4631 | P15: =IF(OR(M15="",N15=""),"N/A",IF(N15<M15,"ERROR","OK")) -> OK | Q15: =IF(Table1[[#This Row],[deal_stage]]="Won",1,0) -> 1 | R15: =IF(Table1[[#This Row],[deal_stage]] ="Lost",1,0) -> 0
A16: 09YE9QOV | B16: Hayden Neloms | C16: =VLOOKUP(Table1[[#This Row],[sales_agent]],'sales team'!A:C,2,FALSE) -> Celia Rouche | D16: =IF(E16="","No account",IFERROR(INDEX(account!$B:$B,MATCH(TRIM(CLEAN(E16)),account!$A:$A,0)),"Not Found")) -> employment | E16: =TRIM(CLEAN(I16)) -> Finjob | F16: =VLOOKUP(Table1[[#This Row],[sales_agent]],'sales team'!A:C,3,FALSE) -> West | G16: =IF(E16="","No account",IFERROR(INDEX(account!$F:$F,MATCH(TRIM(CLEAN(E16)),account!$A:$A,0)),"Not Found")) -> United States | H16: MG Advanced | I16: Finjob | J16: =IF(E16="","No account",IFERROR(INDEX(account!$D:$D,MATCH(TRIM(CLEAN(E16)),account!$A:$A,0)),"Not Found")) -> 2059.9 | K16: =IF(E16="","No account",IFERROR(INDEX(account!$E:$E,MATCH(TRIM(CLEAN(E16)),account!$A:$A,0)),"Not Found")) -> 3644 | L16: Won | M16: 42679 | N16: 42805 | O16: 3393 | P16: =IF(OR(M16="",N16=""),"N/A",IF(N16<M16,"ERROR","OK")) -> OK | Q16: =IF(Table1[[#This Row],[deal_stage]]="Won",1,0) -> 1 | R16: =IF(Table1[[#This Row],[deal_stage]] ="Lost",1,0) -> 0
A17: 3F5MZNEH | B17: Rosalina Dieter | C17: =VLOOKUP(Table1[[#This Row],[sales_agent]],'sales team'!A:C,2,FALSE) -> Celia Rouche | D17: =IF(E17="","No account",IFERROR(INDEX(account!$B:$B,MATCH(TRIM(CLEAN(E17)),account!$A:$A,0)),"Not Found")) -> telecommunications | E17: =TRIM(CLEAN(I17)) -> Sonron | F17: =VLOOKUP(Table1[[#This Row],[sales_agent]],'sales team'!A:C,3,FALSE) -> West | G17: =IF(E17="","No account",IFERROR(INDEX(account!$F:$F,MATCH(TRIM(CLEAN(E17)),account!$A:$A,0)),"Not Found")) -> United States | H17: MG Special | I17: Sonron | J17: =IF(E17="","No account",IFERROR(INDEX(account!$D:$D,MATCH(TRIM(CLEAN(E17)),account!$A:$A,0)),"Not Found")) -> 1699.85 | K17: =IF(E17="","No account",IFERROR(INDEX(account!$E:$E,MATCH(TRIM(CLEAN(E17)),account!$A:$A,0)),"Not Found")) -> 5108 | L17: Lost | M17: 42679 | N17: 42797 | O17: 0 | P17: =IF(OR(M17="",N17=""),"N/A",IF(N17<M17,"ERROR","OK")) -> OK | Q17: =IF(Table1[[#This Row],[deal_stage]]="Won",1,0) -> 0 | R17: =IF(Table1[[#This Row],[deal_stage]] ="Lost",1,0) -> 1
A18: M6WEJXC0 | B18: Rosalina Dieter | C18: =VLOOKUP(Table1[[#This Row],[sales_agent]],'sales team'!A:C,2,FALSE) -> Celia Rouche | D18: =IF(E18="","No account",IFERROR(INDEX(account!$B:$B,MATCH(TRIM(CLEAN(E18)),account!$A:$A,0)),"Not Found")) -> software | E18: =TRIM(CLEAN(I18)) -> Scotfind | F18: =VLOOKUP(Table1[[#This Row],[sales_agent]],'sales team'!A:C,3,FALSE) -> West | G18: =IF(E18="","No account",IFERROR(INDEX(account!$F:$F,MATCH(TRIM(CLEAN(E18)),account!$A:$A,0)),"Not Found")) -> United States | H18: MG Advanced | I18: Scotfind | J18: =IF(E18="","No account",IFERROR(INDEX(account!$D:$D,MATCH(TRIM(CLEAN(E18)),account!$A:$A,0)),"Not Found")) -> 6354.87 | K18: =IF(E18="","No account",IFERROR(INDEX(account!$E:$E,MATCH(TRIM(CLEAN(E18)),account!$A:$A,0)),"Not Found")) -> 16780 | L18: Won | M18: 42679 | N18: 42800 | O18: 3284 | P18: =IF(OR(M18="",N18=""),"N/A",IF(N18<M18,"ERROR","OK")) -> OK | Q18: =IF(Table1[[#This Row],[deal_stage]]="Won",1,0) -> 1 | R18: =IF(Table1[[#This Row],[deal_stage]] ="Lost",1,0) -> 0
A19: 6PTR7VBR | B19: Versie Hillebrand | C19: =VLOOKUP(Table1[[#This Row],[sales_agent]],'sales team'!A:C,2,FALSE) -> Dustin Brinkmann | D19: =IF(E19="","No account",IFERROR(INDEX(account!$B:$B,MATCH(TRIM(CLEAN(E19)),account!$A:$A,0)),"Not Found")) -> telecommunications | E19: =TRIM(CLEAN(I19)) -> Treequote | F19: =VLOOKUP(Table1[[#This Row],[sales_agent]],'sales team'!A:C,3,FALSE) -> Central | G19: =IF(E19="","No account",IFERROR(INDEX(account!$F:$F,MATCH(TRIM(CLEAN(E19)),account!$A:$A,0)),"Not Found")) -> United States | H19: MG Special | I19: Treequote | J19: =IF(E19="","No account",IFERROR(INDEX(account!$D:$D,MATCH(TRIM(CLEAN(E19)),account!$A:$A,0)),"Not Found")) -> 5266.09 | K19: =IF(E19="","No account",IFERROR(INDEX(account!$E:$E,MATCH(TRIM(CLEAN(E19)),account!$A:$A,0)),"Not Found")) -> 8595 | L19: Won | M19: 42680 | N19: 42799 | O19: 61 | P19: =IF(OR(M19="",N19=""),"N/A",IF(N19<M19,"ERROR","OK")) -> OK | Q19: =IF(Table1[[#This Row],[deal_stage]]="Won",1,0) -> 1 | R19: =IF(Table1[[#This Row],[deal_stage]] ="Lost",1,0) -> 0
A20: 902REDPA | B20: Daniell Hammack | C20: =VLOOKUP(Table1[[#This Row],[sales_agent]],'sales team'!A:C,2,FALSE) -> Rocco Neubert | D20: =IF(E20="","No account",IFERROR(INDEX(account!$B:$B,MATCH(TRIM(CLEAN(E20)),account!$A:$A,0)),"Not Found")) -> entertainment | E20: =TRIM(CLEAN(I20)) -> Xx-zobam | F20: =VLOOKUP(Table1[[#This Row],[sales_agent]],'sales team'!A:C,3,FALSE) -> East | G20: =IF(E20="","No account",IFERROR(INDEX(account!$F:$F,MATCH(TRIM(CLEAN(E20)),account!$A:$A,0)),"Not Found")) -> United States | H20: GTXPro | I20: Xx-zobam | J20: =IF(E20="","No account",IFERROR(INDEX(account!$D:$D,MATCH(TRIM(CLEAN(E20)),account!$A:$A,0)),"Not Found")) -> 3838.39 | K20: =IF(E20="","No account",IFERROR(INDEX(account!$E:$E,MATCH(TRIM(CLEAN(E20)),account!$A:$A,0)),"Not Found")) -> 8274 | L20: Lost | M20: 42681 | N20: 42803 | O20: 0 | P20: =IF(OR(M20="",N20=""),"N/A",IF(N20<M20,"ERROR","OK")) -> OK | Q20: =IF(Table1[[#This Row],[deal_stage]]="Won",1,0) -> 0 | R20: =IF(Table1[[#This Row],[deal_stage]] ="Lost",1,0) -> 1
A21: 5J9CMGDV | B21: Elease Gluck | C21: =VLOOKUP(Table1[[#This Row],[sales_agent]],'sales team'!A:C,2,FALSE) -> Celia Rouche | D21: =IF(E21="","No account",IFERROR(INDEX(account!$B:$B,MATCH(TRIM(CLEAN(E21)),account!$A:$A,0)),"Not Found")) -> telecommunications | E21: =TRIM(CLEAN(I21)) -> Rantouch | F21: =VLOOKUP(Table1[[#This Row],[sales_agent]],'sales team'!A:C,3,FALSE) -> West | G21: =IF(E21="","No account",IFERROR(INDEX(account!$F:$F,MATCH(TRIM(CLEAN(E21)),account!$A:$A,0)),"Not Found")) -> United States | H21: MG Special | I21: Rantouch | J21: =IF(E21="","No account",IFERROR(INDEX(account!$D:$D,MATCH(TRIM(CLEAN(E21)),account!$A:$A,0)),"Not Found")) -> 1188.42 | K21: =IF(E21="","No account",IFERROR(INDEX(account!$E:$E,MATCH(TRIM(CLEAN(E21)),account!$A:$A,0)),"Not Found")) -> 3015 | L21: Won | M21: 42681 | N21: 42802 | O21: 46 | P21: =IF(OR(M21="",N21=""),"N/A",IF(N21<M21,"ERROR","OK")) -> OK | Q21: =IF(Table1[[#This Row],[deal_stage]]="Won",1,0) -> 1 | R21: =IF(Table1[[#This Row],[deal_stage]] ="Lost",1,0) -> 0
A22: JJXRR8R6 | B22: James Ascencio | C22: =VLOOKUP(Table1[[#This Row],[sales_agent]],'sales team'!A:C,2,FALSE) -> Summer Sewald | D22: =IF(E22="","No account",IFERROR(INDEX(account!$B:$B,MATCH(TRIM(CLEAN(E22)),account!$A:$A,0)),"Not Found")) -> retail | E22: =TRIM(CLEAN(I22)) -> Fasehatice | F22: =VLOOKUP(Table1[[#This Row],[sales_agent]],'sales team'!A:C,3,FALSE) -> West | G22: =IF(E22="","No account",IFERROR(INDEX(account!$F:$F,MATCH(TRIM(CLEAN(E22)),account!$A:$A,0)),"Not Found")) -> United States | H22: GTX Plus Pro | I22: Fasehatice | J22: =IF(E22="","No account",IFERROR(INDEX(account!$D:$D,MATCH(TRIM(CLEAN(E22)),account!$A:$A,0)),"Not Found")) -> 4968.91 | K22: =IF(E22="","No account",IFERROR(INDEX(account!$E:$E,MATCH(TRIM(CLEAN(E22)),account!$A:$A,0)),"Not Found")) -> 7523 | L22: Lost | M22: 42681 | N22: 42811 | O22: 0 | P22: =IF(OR(M22="",N22=""),"N/A",IF(N22<M22,"ERROR","OK")) -> OK | Q22: =IF(Table1[[#This Row],[deal_stage]]="Won",1,0) -> 0 | R22: =IF(Table1[[#This Row],[deal_stage]] ="Lost",1,0) -> 1
A23: WF4HA5NW | B23: Moses Frase | C23: =VLOOKUP(Table1[[#This Row],[sales_agent]],'sales team'!A:C,2,FALSE) -> Dustin Brinkmann | D23: =IF(E23="","No account",IFERROR(INDEX(account!$B:$B,MATCH(TRIM(CLEAN(E23)),account!$A:$A,0)),"Not Found")) -> medical | E23: =TRIM(CLEAN(I23)) -> Ron-tech | F23: =VLOOKUP(Table1[[#This Row],[sales_agent]],'sales team'!A:C,3,FALSE) -> Central | G23: =IF(E23="","No account",IFERROR(INDEX(account!$F:$F,MATCH(TRIM(CLEAN(E23)),account!$A:$A,0)),"Not Found")) -> United States | H23: MG Special | I23: Ron-tech | J23: =IF(E23="","No account",IFERROR(INDEX(account!$D:$D,MATCH(TRIM(CLEAN(E23)),account!$A:$A,0)),"Not Found")) -> 3922.42 | K23: =IF(E23="","No account",IFERROR(INDEX(account!$E:$E,MATCH(TRIM(CLEAN(E23)),account!$A:$A,0)),"Not Found")) -> 6837 | L23: Won | M23: 42681 | N23: 42812 | O23: 50 | P23: =IF(OR(M23="",N23=""),"N/A",IF(N23<M23,"ERROR","OK")) -> OK | Q23: =IF(Table1[[#This Row],[deal_stage]]="Won",1,0) -> 1 | R23: =IF(Table1[[#This Row],[deal_stage]] ="Lost",1,0) -> 0
... A26: SBCR987L | B26: Kami Bicknell | C26: =VLOOKUP(Table1[[#This Row],[sales_agent]],'sales team'!A:C,2,FALSE) -> Summer Sewald | D26: =IF(E26="","No account",IFERROR(INDEX(account!$B:$B,MATCH(TRIM(CLEAN(E26)),account!$A:$A,0)),"Not Found")) -> entertainment | E26: =TRIM(CLEAN(I26)) -> Zoomit | F26: =VLOOKUP(Table1[[#This Row],[sales_agent]],'sales team'!A:C,3,FALSE) -> West | G26: =IF(E26="","No account",IFERROR(INDEX(account!$F:$F,MATCH(TRIM(CLEAN(E26)),account!$A:$A,0)),"Not Found")) -> United States | H26: GTX Basic | I26: Zoomit | J26: =IF(E26="","No account",IFERROR(INDEX(account!$D:$D,MATCH(TRIM(CLEAN(E26)),account!$A:$A,0)),"Not Found")) -> 324.19 | K26: =IF(E26="","No account",IFERROR(INDEX(account!$E:$E,MATCH(TRIM(CLEAN(E26)),account!$A:$A,0)),"Not Found")) -> 978 | L26: Won | M26: 42684 | N26: 42817 | O26: 590 | P26: =IF(OR(M26="",N26=""),"N/A",IF(N26<M26,"ERROR","OK")) -> OK | Q26: =IF(Table1[[#This Row],[deal_stage]]="Won",1,0) -> 1 | R26: =IF(Table1[[#This Row],[deal_stage]] ="Lost",1,0) -> 0
A27: UP409DSB | B27: Maureen Marcano | C27: =VLOOKUP(Table1[[#This Row],[sales_agent]],'sales team'!A:C,2,FALSE) -> Summer Sewald | D27: =IF(E27="","No account",IFERROR(INDEX(account!$B:$B,MATCH(TRIM(CLEAN(E27)),account!$A:$A,0)),"Not Found")) -> retail | E27: =TRIM(CLEAN(I27)) -> Ganjaflex | F27: =VLOOKUP(Table1[[#This Row],[sales_agent]],'sales team'!A:C,3,FALSE) -> West | G27: =IF(E27="","No account",IFERROR(INDEX(account!$F:$F,MATCH(TRIM(CLEAN(E27)),account!$A:$A,0)),"Not Found")) -> Japan | H27: MG Advanced | I27: Ganjaflex | J27: =IF(E27="","No account",IFERROR(INDEX(account!$D:$D,MATCH(TRIM(CLEAN(E27)),account!$A:$A,0)),"Not Found")) -> 5158.71 | K27: =IF(E27="","No account",IFERROR(INDEX(account!$E:$E,MATCH(TRIM(CLEAN(E27)),account!$A:$A,0)),"Not Found")) -> 17479 | L27: Engaging | M27: 42684 | P27: =IF(OR(M27="",N27=""),"N/A",IF(N27<M27,"ERROR","OK")) -> N/A | Q27: =IF(Table1[[#This Row],[deal_stage]]="Won",1,0) -> 0 | R27: =IF(Table1[[#This Row],[deal_stage]] ="Lost",1,0) -> 0
A28: JSD4APT2 | B28: Versie Hillebrand | C28: =VLOOKUP(Table1[[#This Row],[sales_agent]],'sales team'!A:C,2,FALSE) -> Dustin Brinkmann | D28: =IF(E28="","No account",IFERROR(INDEX(account!$B:$B,MATCH(TRIM(CLEAN(E28)),account!$A:$A,0)),"Not Found")) -> medical | E28: =TRIM(CLEAN(I28)) -> Bioholding | F28: =VLOOKUP(Table1[[#This Row],[sales_agent]],'sales team'!A:C,3,FALSE) -> Central | G28: =IF(E28="","No account",IFERROR(INDEX(account!$F:$F,MATCH(TRIM(CLEAN(E28)),account!$A:$A,0)),"Not Found")) -> Philipines | H28: MG Special | I28: Bioholding | J28: =IF(E28="","No account",IFERROR(INDEX(account!$D:$D,MATCH(TRIM(CLEAN(E28)),account!$A:$A,0)),"Not Found")) -> 587.34 | K28: =IF(E28="","No account",IFERROR(INDEX(account!$E:$E,MATCH(TRIM(CLEAN(E28)),account!$A:$A,0)),"Not Found")) -> 1356 | L28: Won | M28: 42684 | N28: 42806 | O28: 61 | P28: =IF(OR(M28="",N28=""),"N/A",IF(N28<M28,"ERROR","OK")) -> OK | Q28: =IF(Table1[[#This Row],[deal_stage]]="Won",1,0) -> 1 | R28: =IF(Table1[[#This Row],[deal_stage]] ="Lost",1,0) -> 0
A29: AO9Z2D17 | B29: Violet Mclelland | C29: =VLOOKUP(Table1[[#This Row],[sales_agent]],'sales team'!A:C,2,FALSE) -> Cara Losch | D29: =IF(E29="","No account",IFERROR(INDEX(account!$B:$B,MATCH(TRIM(CLEAN(E29)),account!$A:$A,0)),"Not Found")) -> entertainment | E29: =TRIM(CLEAN(I29)) -> Xx-zobam | F29: =VLOOKUP(Table1[[#This Row],[sales_agent]],'sales team'!A:C,3,FALSE) -> East | G29: =IF(E29="","No account",IFERROR(INDEX(account!$F:$F,MATCH(TRIM(CLEAN(E29)),account!$A:$A,0)),"Not Found")) -> United States | H29: GTX Plus Pro | I29: Xx-zobam | J29: =IF(E29="","No account",IFERROR(INDEX(account!$D:$D,MATCH(TRIM(CLEAN(E29)),account!$A:$A,0)),"Not Found")) -> 3838.39 | K29: =IF(E29="","No account",IFERROR(INDEX(account!$E:$E,MATCH(TRIM(CLEAN(E29)),account!$A:$A,0)),"Not Found")) -> 8274 | L29: Lost | M29: 42684 | N29: 42805 | O29: 0 | P29: =IF(OR(M29="",N29=""),"N/A",IF(N29<M29,"ERROR","OK")) -> OK | Q29: =IF(Table1[[#This Row],[deal_stage]]="Won",1,0) -> 0 | R29: =IF(Table1[[#This Row],[deal_stage]] ="Lost",1,0) -> 1
A30: 5M58DTJK | B30: Elease Gluck | C30: =VLOOKUP(Table1[[#This Row],[sales_agent]],'sales team'!A:C,2,FALSE) -> Celia Rouche | D30: =IF(E30="","No account",IFERROR(INDEX(account!$B:$B,MATCH(TRIM(CLEAN(E30)),account!$A:$A,0)),"Not Found")) -> entertainment | E30: =TRIM(CLEAN(I30)) -> Cheers | F30: =VLOOKUP(Table1[[#This Row],[sales_agent]],'sales team'!A:C,3,FALSE) -> West | G30: =IF(E30="","No account",IFERROR(INDEX(account!$F:$F,MATCH(TRIM(CLEAN(E30)),account!$A:$A,0)),"Not Found")) -> United States | H30: MG Special | I30: Cheers | J30: =IF(E30="","No account",IFERROR(INDEX(account!$D:$D,MATCH(TRIM(CLEAN(E30)),account!$A:$A,0)),"Not Found")) -> 4269.9 | K30: =IF(E30="","No account",IFERROR(INDEX(account!$E:$E,MATCH(TRIM(CLEAN(E30)),account!$A:$A,0)),"Not Found")) -> 6472 | L30: Won | M30: 42685 | N30: 42799 | O30: 58 | P30: =IF(OR(M30="",N30=""),"N/A",IF(N30<M30,"ERROR","OK")) -> OK | Q30: =IF(Table1[[#This Row],[deal_stage]]="Won",1,0) -> 1 | R30: =IF(Table1[[#This Row],[deal_stage]] ="Lost",1,0) -> 0
A31: KNY1OSAB | B31: Maureen Marcano | C31: =VLOOKUP(Table1[[#This Row],[sales_agent]],'sales team'!A:C,2,FALSE) -> Summer Sewald | D31: =IF(E31="","No account",IFERROR(INDEX(account!$B:$B,MATCH(TRIM(CLEAN(E31)),account!$A:$A,0)),"Not Found")) -> medical | E31: =TRIM(CLEAN(I31)) -> Labdrill | F31: =VLOOKUP(Table1[[#This Row],[sales_agent]],'sales team'!A:C,3,FALSE) -> West | G31: =IF(E31="","No account",IFERROR(INDEX(account!$F:$F,MATCH(TRIM(CLEAN(E31)),account!$A:$A,0)),"Not Found")) -> United States | H31: GTXPro | I31: Labdrill | J31: =IF(E31="","No account",IFERROR(INDEX(account!$D:$D,MATCH(TRIM(CLEAN(E31)),account!$A:$A,0)),"Not Found")) -> 2741.37 | K31: =IF(E31="","No account",IFERROR(INDEX(account!$E:$E,MATCH(TRIM(CLEAN(E31)),account!$A:$A,0)),"Not Found")) -> 9226 | L31: Won | M31: 42685 | N31: 42808 | O31: 4899 | P31: =IF(OR(M31="",N31=""),"N/A",IF(N31<M31,"ERROR","OK")) -> OK | Q31: =IF(Table1[[#This Row],[deal_stage]]="Won",1,0) -> 1 | R31: =IF(Table1[[#This Row],[deal_stage]] ="Lost",1,0) -> 0
A32: EAZDUUM9 | B32: Rosie Papadopoulos | C32: =VLOOKUP(Table1[[#This Row],[sales_agent]],'sales team'!A:C,2,FALSE) -> Cara Losch | D32: =IF(E32="","No account",IFERROR(INDEX(account!$B:$B,MATCH(TRIM(CLEAN(E32)),account!$A:$A,0)),"Not Found")) -> software | E32: =TRIM(CLEAN(I32)) -> Zotware | F32: =VLOOKUP(Table1[[#This Row],[sales_agent]],'sales team'!A:C,3,FALSE) -> East | G32: =IF(E32="","No account",IFERROR(INDEX(account!$F:$F,MATCH(TRIM(CLEAN(E32)),account!$A:$A,0)),"Not Found")) -> United States | H32: MG Advanced | I32: Zotware | J32: =IF(E32="","No account",IFERROR(INDEX(account!$D:$D,MATCH(TRIM(CLEAN(E32)),account!$A:$A,0)),"Not Found")) -> 4478.47 | K32: =IF(E32="","No account",IFERROR(INDEX(account!$E:$E,MATCH(TRIM(CLEAN(E32)),account!$A:$A,0)),"Not Found")) -> 13809 | L32: Lost | M32: 42685 | N32: 42795 | O32: 0 | P32: =IF(OR(M32="",N32=""),"N/A",IF(N32<M32,"ERROR","OK")) -> OK | Q32: =IF(Table1[[#This Row],[deal_stage]]="Won",1,0) -> 0 | R32: =IF(Table1[[#This Row],[deal_stage]] ="Lost",1,0) -> 1
A33: 2STUSOFE | B33: Versie Hillebrand | C33: =VLOOKUP(Table1[[#This Row],[sales_agent]],'sales team'!A:C,2,FALSE) -> Dustin Brinkmann | D33: =IF(E33="","No account",IFERROR(INDEX(account!$B:$B,MATCH(TRIM(CLEAN(E33)),account!$A:$A,0)),"Not Found")) -> marketing | E33: =TRIM(CLEAN(I33)) -> dambase | F33: =VLOOKUP(Table1[[#This Row],[sales_agent]],'sales team'!A:C,3,FALSE) -> Central | G33: =IF(E33="","No account",IFERROR(INDEX(account!$F:$F,MATCH(TRIM(CLEAN(E33)),account!$A:$A,0)),"Not Found")) -> United States | H33: MG Special | I33: dambase | J33: =IF(E33="","No account",IFERROR(INDEX(account!$D:$D,MATCH(TRIM(CLEAN(E33)),account!$A:$A,0)),"Not Found")) -> 2173.98 | K33: =IF(E33="","No account",IFERROR(INDEX(account!$E:$E,MATCH(TRIM(CLEAN(E33)),account!$A:$A,0)),"Not Found")) -> 2928 | L33: Won | M33: 42685 | N33: 42797 | O33: 67 | P33: =IF(OR(M33="",N33=""),"N/A",IF(N33<M33,"ERROR","OK")) -> OK | Q33: =IF(Table1[[#This Row],[deal_stage]]="Won",1,0) -> 1 | R33: =IF(Table1[[#This Row],[deal_stage]] ="Lost",1,0) -> 0
A34: JYKM0B00 | B34: James Ascencio | C34: =VLOOKUP(Table1[[#This Row],[sales_agent]],'sales team'!A:C,2,FALSE) -> Summer Sewald | D34: =IF(E34="","No account",IFERROR(INDEX(account!$B:$B,MATCH(TRIM(CLEAN(E34)),account!$A:$A,0)),"Not Found")) -> finance | E34: =TRIM(CLEAN(I34)) -> Xx-holding | F34: =VLOOKUP(Table1[[#This Row],[sales_agent]],'sales team'!A:C,3,FALSE) -> West | G34: =IF(E34="","No account",IFERROR(INDEX(account!$F:$F,MATCH(TRIM(CLEAN(E34)),account!$A:$A,0)),"Not Found")) -> United States | H34: GTXPro | I34: Xx-holding | J34: =IF(E34="","No account",IFERROR(INDEX(account!$D:$D,MATCH(TRIM(CLEAN(E34)),account!$A:$A,0)),"Not Found")) -> 7537.24 | K34: =IF(E34="","No account",IFERROR(INDEX(account!$E:$E,MATCH(TRIM(CLEAN(E34)),account!$A:$A,0)),"Not Found")) -> 20293 | L34: Won | M34: 42686 | N34: 42800 | O34: 4338 | P34: =IF(OR(M34="",N34=""),"N/A",IF(N34<M34,"ERROR","OK")) -> OK | Q34: =IF(Table1[[#This Row],[deal_stage]]="Won",1,0) -> 1 | R34: =IF(Table1[[#This Row],[deal_stage]] ="Lost",1,0) -> 0
A35: KU28360J | B35: Kary Hendrixson | C35: =VLOOKUP(Table1[[#This Row],[sales_agent]],'sales team'!A:C,2,FALSE) -> Summer Sewald | D35: =IF(E35="","No account",IFERROR(INDEX(account!$B:$B,MATCH(TRIM(CLEAN(E35)),account!$A:$A,0)),"Not Found")) -> retail | E35: =TRIM(CLEAN(I35)) -> Fasehatice | F35: =VLOOKUP(Table1[[#This Row],[sales_agent]],'sales team'!A:C,3,FALSE) -> West | G35: =IF(E35="","No account",IFERROR(INDEX(account!$F:$F,MATCH(TRIM(CLEAN(E35)),account!$A:$A,0)),"Not Found")) -> United States | H35: GTX Basic | I35: Fasehatice | J35: =IF(E35="","No account",IFERROR(INDEX(account!$D:$D,MATCH(TRIM(CLEAN(E35)),account!$A:$A,0)),"Not Found")) -> 4968.91 | K35: =IF(E35="","No account",IFERROR(INDEX(account!$E:$E,MATCH(TRIM(CLEAN(E35)),account!$A:$A,0)),"Not Found")) -> 7523 | L35: Won | M35: 42686 | N35: 42813 | O35: 578 | P35: =IF(OR(M35="",N35=""),"N/A",IF(N35<M35,"ERROR","OK")) -> OK | Q35: =IF(Table1[[#This Row],[deal_stage]]="Won",1,0) -> 1 | R35: =IF(Table1[[#This Row],[deal_stage]] ="Lost",1,0) -> 0
A36: N4SD17JR | B36: Reed Clapper | C36: =VLOOKUP(Table1[[#This Row],[sales_agent]],'sales team'!A:C,2,FALSE) -> Rocco Neubert | D36: =IF(E36="","No account",IFERROR(INDEX(account!$B:$B,MATCH(TRIM(CLEAN(E36)),account!$A:$A,0)),"Not Found")) -> technolgy | E36: =TRIM(CLEAN(I36)) -> Acme Corporation | F36: =VLOOKUP(Table1[[#This Row],[sales_agent]],'sales team'!A:C,3,FALSE) -> East | G36: =IF(E36="","No account",IFERROR(INDEX(account!$F:$F,MATCH(TRIM(CLEAN(E36)),account!$A:$A,0)),"Not Found")) -> United States | H36: GTX Basic | I36: Acme Corporation | J36: =IF(E36="","No account",IFERROR(INDEX(account!$D:$D,MATCH(TRIM(CLEAN(E36)),account!$A:$A,0)),"Not Found")) -> 1100.04 | K36: =IF(E36="","No account",IFERROR(INDEX(account!$E:$E,MATCH(TRIM(CLEAN(E36)),account!$A:$A,0)),"Not Found")) -> 2822 | L36: Won | M36: 42686 | N36: 42795 | O36: 556 | P36: =IF(OR(M36="",N36=""),"N/A",IF(N36<M36,"ERROR","OK")) -> OK | Q36: =IF(Table1[[#This Row],[deal_stage]]="Won",1,0) -> 1 | R36: =IF(Table1[[#This Row],[deal_stage]] ="Lost",1,0) -> 0
A37: E67P9Y3Q | B37: Rosalina Dieter | C37: =VLOOKUP(Table1[[#This Row],[sales_agent]],'sales team'!A:C,2,FALSE) -> Celia Rouche | D37: =IF(E37="","No account",IFERROR(INDEX(account!$B:$B,MATCH(TRIM(CLEAN(E37)),account!$A:$A,0)),"Not Found")) -> services | E37: =TRIM(CLEAN(I37)) -> Green-Plus | F37: =VLOOKUP(Table1[[#This Row],[sales_agent]],'sales team'!A:C,3,FALSE) -> West | G37: =IF(E37="","No account",IFERROR(INDEX(account!$F:$F,MATCH(TRIM(CLEAN(E37)),account!$A:$A,0)),"Not Found")) -> United States | H37: GTX Basic | I37: Green-Plus | J37: =IF(E37="","No account",IFERROR(INDEX(account!$D:$D,MATCH(TRIM(CLEAN(E37)),account!$A:$A,0)),"Not Found")) -> 692.19 | K37: =IF(E37="","No account",IFERROR(INDEX(account!$E:$E,MATCH(TRIM(CLEAN(E37)),account!$A:$A,0)),"Not Found")) -> 1922 | L37: Won | M37: 42686 | N37: 42797 | O37: 635 | P37: =IF(OR(M37="",N37=""),"N/A",IF(N37<M37,"ERROR","OK")) -> OK | Q37: =IF(Table1[[#This Row],[deal_stage]]="Won",1,0) -> 1 | R37: =IF(Table1[[#This Row],[deal_stage]] ="Lost",1,0) -> 0
A38: AT3MMVIS | B38: Wilburn Farren | C38: =VLOOKUP(Table1[[#This Row],[sales_agent]],'sales team'!A:C,2,FALSE) -> Cara Losch | D38: =IF(E38="","No account",IFERROR(INDEX(account!$B:$B,MATCH(TRIM(CLEAN(E38)),account!$A:$A,0)),"Not Found")) -> medical | E38: =TRIM(CLEAN(I38)) -> The New York Inquirer | F38: =VLOOKUP(Table1[[#This Row],[sales_agent]],'sales team'!A:C,3,FALSE) -> East | G38: =IF(E38="","No account",IFERROR(INDEX(account!$F:$F,MATCH(TRIM(CLEAN(E38)),account!$A:$A,0)),"Not Found")) -> United States | H38: MG Advanced | I38: The New York Inquirer | J38: =IF(E38="","No account",IFERROR(INDEX(account!$D:$D,MATCH(TRIM(CLEAN(E38)),account!$A:$A,0)),"Not Found")) -> 439.21 | K38: =IF(E38="","No account",IFERROR(INDEX(account!$E:$E,MATCH(TRIM(CLEAN(E38)),account!$A:$A,0)),"Not Found")) -> 792 | L38: Won | M38: 42686 | N38: 42801 | O38: 3045 | P38: =IF(OR(M38="",N38=""),"N/A",IF(N38<M38,"ERROR","OK")) -> OK | Q38: =IF(Table1[[#This Row],[deal_stage]]="Won",1,0) -> 1 | R38: =IF(Table1[[#This Row],[deal_stage]] ="Lost",1,0) -> 0
A39: REJ11LRY | B39: Garret Kinder | C39: =VLOOKUP(Table1[[#This Row],[sales_agent]],'sales team'!A:C,2,FALSE) -> Cara Losch | D39: =IF(E39="","No account",IFERROR(INDEX(account!$B:$B,MATCH(TRIM(CLEAN(E39)),account!$A:$A,0)),"Not Found")) -> marketing | E39: =TRIM(CLEAN(I39)) -> Mathtouch | F39: =VLOOKUP(Table1[[#This Row],[sales_agent]],'sales team'!A:C,3,FALSE) -> East | G39: =IF(E39="","No account",IFERROR(INDEX(account!$F:$F,MATCH(TRIM(CLEAN(E39)),account!$A:$A,0)),"Not Found")) -> Jordan | H39: GTX Plus Basic | I39: Mathtouch | J39: =IF(E39="","No account",IFERROR(INDEX(account!$D:$D,MATCH(TRIM(CLEAN(E39)),account!$A:$A,0)),"Not Found")) -> 3027.46 | K39: =IF(E39="","No account",IFERROR(INDEX(account!$E:$E,MATCH(TRIM(CLEAN(E39)),account!$A:$A,0)),"Not Found")) -> 9516 | L39: Won | M39: 42687 | N39: 42808 | O39: 1233 | P39: =IF(OR(M39="",N39=""),"N/A",IF(N39<M39,"ERROR","OK")) -> OK | Q39: =IF(Table1[[#This Row],[deal_stage]]="Won",1,0) -> 1 | R39: =IF(Table1[[#This Row],[deal_stage]] ="Lost",1,0) -> 0
... A43: CZVN09WN | B43: Darcel Schlecht | C43: =VLOOKUP(Table1[[#This Row],[sales_agent]],'sales team'!A:C,2,FALSE) -> Melvin Marxen | D43: =IF(E43="","No account",IFERROR(INDEX(account!$B:$B,MATCH(TRIM(CLEAN(E43)),account!$A:$A,0)),"Not Found")) -> marketing | E43: =TRIM(CLEAN(I43)) -> Konmatfix | F43: =VLOOKUP(Table1[[#This Row],[sales_agent]],'sales team'!A:C,3,FALSE) -> Central | G43: =IF(E43="","No account",IFERROR(INDEX(account!$F:$F,MATCH(TRIM(CLEAN(E43)),account!$A:$A,0)),"Not Found")) -> United States | H43: GTX Plus Basic | I43: Konmatfix | J43: =IF(E43="","No account",IFERROR(INDEX(account!$D:$D,MATCH(TRIM(CLEAN(E43)),account!$A:$A,0)),"Not Found")) -> 375.43 | K43: =IF(E43="","No account",IFERROR(INDEX(account!$E:$E,MATCH(TRIM(CLEAN(E43)),account!$A:$A,0)),"Not Found")) -> 1190 | L43: Won | M43: 42688 | N43: 42814 | O43: 1170 | P43: =IF(OR(M43="",N43=""),"N/A",IF(N43<M43,"ERROR","OK")) -> OK | Q43: =IF(Table1[[#This Row],[deal_stage]]="Won",1,0) -> 1 | R43: =IF(Table1[[#This Row],[deal_stage]] ="Lost",1,0) -> 0
A44: EG7OFLFR | B44: Kami Bicknell | C44: =VLOOKUP(Table1[[#This Row],[sales_agent]],'sales team'!A:C,2,FALSE) -> Summer Sewald | D44: =IF(E44="","No account",IFERROR(INDEX(account!$B:$B,MATCH(TRIM(CLEAN(E44)),account!$A:$A,0)),"Not Found")) -> No account | E44: =TRIM(CLEAN(I44)) | F44: =VLOOKUP(Table1[[#This Row],[sales_agent]],'sales team'!A:C,3,FALSE) -> West | G44: =IF(E44="","No account",IFERROR(INDEX(account!$F:$F,MATCH(TRIM(CLEAN(E44)),account!$A:$A,0)),"Not Found")) -> No account | H44: GTX Basic | J44: =IF(E44="","No account",IFERROR(INDEX(account!$D:$D,MATCH(TRIM(CLEAN(E44)),account!$A:$A,0)),"Not Found")) -> No account | K44: =IF(E44="","No account",IFERROR(INDEX(account!$E:$E,MATCH(TRIM(CLEAN(E44)),account!$A:$A,0)),"Not Found")) -> No account | L44: Engaging | M44: 42688 | P44: =IF(OR(M44="",N44=""),"N/A",IF(N44<M44,"ERROR","OK")) -> N/A | Q44: =IF(Table1[[#This Row],[deal_stage]]="Won",1,0) -> 0 | R44: =IF(Table1[[#This Row],[deal_stage]] ="Lost",1,0) -> 0
A45: 30UQWUKB | B45: Marty Freudenburg | C45: =VLOOKUP(Table1[[#This Row],[sales_agent]],'sales team'!A:C,2,FALSE) -> Melvin Marxen | D45: =IF(E45="","No account",IFERROR(INDEX(account!$B:$B,MATCH(TRIM(CLEAN(E45)),account!$A:$A,0)),"Not Found")) -> retail | E45: =TRIM(CLEAN(I45)) -> Genco Pura Olive Oil Company | F45: =VLOOKUP(Table1[[#This Row],[sales_agent]],'sales team'!A:C,3,FALSE) -> Central | G45: =IF(E45="","No account",IFERROR(INDEX(account!$F:$F,MATCH(TRIM(CLEAN(E45)),account!$A:$A,0)),"Not Found")) -> Italy | H45: GTX Plus Basic | I45: Genco Pura Olive Oil Company | J45: =IF(E45="","No account",IFERROR(INDEX(account!$D:$D,MATCH(TRIM(CLEAN(E45)),account!$A:$A,0)),"Not Found")) -> 894.33 | K45: =IF(E45="","No account",IFERROR(INDEX(account!$E:$E,MATCH(TRIM(CLEAN(E45)),account!$A:$A,0)),"Not Found")) -> 1635 | L45: Won | M45: 42689 | N45: 42814 | O45: 1162 | P45: =IF(OR(M45="",N45=""),"N/A",IF(N45<M45,"ERROR","OK")) -> OK | Q45: =IF(Table1[[#This Row],[deal_stage]]="Won",1,0) -> 1 | R45: =IF(Table1[[#This Row],[deal_stage]] ="Lost",1,0) -> 0
A46: OLVI7L8M | B46: Cassey Cress | C46: =VLOOKUP(Table1[[#This Row],[sales_agent]],'sales team'!A:C,2,FALSE) -> Rocco Neubert | D46: =IF(E46="","No account",IFERROR(INDEX(account!$B:$B,MATCH(TRIM(CLEAN(E46)),account!$A:$A,0)),"Not Found")) -> No account | E46: =TRIM(CLEAN(I46)) | F46: =VLOOKUP(Table1[[#This Row],[sales_agent]],'sales team'!A:C,3,FALSE) -> East | G46: =IF(E46="","No account",IFERROR(INDEX(account!$F:$F,MATCH(TRIM(CLEAN(E46)),account!$A:$A,0)),"Not Found")) -> No account | H46: GTXPro | J46: =IF(E46="","No account",IFERROR(INDEX(account!$D:$D,MATCH(TRIM(CLEAN(E46)),account!$A:$A,0)),"Not Found")) -> No account | K46: =IF(E46="","No account",IFERROR(INDEX(account!$E:$E,MATCH(TRIM(CLEAN(E46)),account!$A:$A,0)),"Not Found")) -> No account | L46: Engaging | M46: 42690 | P46: =IF(OR(M46="",N46=""),"N/A",IF(N46<M46,"ERROR","OK")) -> N/A | Q46: =IF(Table1[[#This Row],[deal_stage]]="Won",1,0) -> 0 | R46: =IF(Table1[[#This Row],[deal_stage]] ="Lost",1,0) -> 0
A47: 97UN20YY | B47: Darcel Schlecht | C47: =VLOOKUP(Table1[[#This Row],[sales_agent]],'sales team'!A:C,2,FALSE) -> Melvin Marxen | D47: =IF(E47="","No account",IFERROR(INDEX(account!$B:$B,MATCH(TRIM(CLEAN(E47)),account!$A:$A,0)),"Not Found")) -> technolgy | E47: =TRIM(CLEAN(I47)) -> Conecom | F47: =VLOOKUP(Table1[[#This Row],[sales_agent]],'sales team'!A:C,3,FALSE) -> Central | G47: =IF(E47="","No account",IFERROR(INDEX(account!$F:$F,MATCH(TRIM(CLEAN(E47)),account!$A:$A,0)),"Not Found")) -> United States | H47: MG Advanced | I47: Conecom | J47: =IF(E47="","No account",IFERROR(INDEX(account!$D:$D,MATCH(TRIM(CLEAN(E47)),account!$A:$A,0)),"Not Found")) -> 1520.66 | K47: =IF(E47="","No account",IFERROR(INDEX(account!$E:$E,MATCH(TRIM(CLEAN(E47)),account!$A:$A,0)),"Not Found")) -> 1806 | L47: Won | M47: 42690 | N47: 42808 | O47: 3725 | P47: =IF(OR(M47="",N47=""),"N/A",IF(N47<M47,"ERROR","OK")) -> OK | Q47: =IF(Table1[[#This Row],[deal_stage]]="Won",1,0) -> 1 | R47: =IF(Table1[[#This Row],[deal_stage]] ="Lost",1,0) -> 0
A48: JXLERZ9O | B48: Kary Hendrixson | C48: =VLOOKUP(Table1[[#This Row],[sales_agent]],'sales team'!A:C,2,FALSE) -> Summer Sewald | D48: =IF(E48="","No account",IFERROR(INDEX(account!$B:$B,MATCH(TRIM(CLEAN(E48)),account!$A:$A,0)),"Not Found")) -> finance | E48: =TRIM(CLEAN(I48)) -> Golddex | F48: =VLOOKUP(Table1[[#This Row],[sales_agent]],'sales team'!A:C,3,FALSE) -> West | G48: =IF(E48="","No account",IFERROR(INDEX(account!$F:$F,MATCH(TRIM(CLEAN(E48)),account!$A:$A,0)),"Not Found")) -> United States | H48: GTX Basic | I48: Golddex | J48: =IF(E48="","No account",IFERROR(INDEX(account!$D:$D,MATCH(TRIM(CLEAN(E48)),account!$A:$A,0)),"Not Found")) -> 52.5 | K48: =IF(E48="","No account",IFERROR(INDEX(account!$E:$E,MATCH(TRIM(CLEAN(E48)),account!$A:$A,0)),"Not Found")) -> 165 | L48: Won | M48: 42690 | N48: 42825 | O48: 559 | P48: =IF(OR(M48="",N48=""),"N/A",IF(N48<M48,"ERROR","OK")) -> OK | Q48: =IF(Table1[[#This Row],[deal_stage]]="Won",1,0) -> 1 | R48: =IF(Table1[[#This Row],[deal_stage]] ="Lost",1,0) -> 0
A49: 6ROE69W5 | B49: Rosalina Dieter | C49: =VLOOKUP(Table1[[#This Row],[sales_agent]],'sales team'!A:C,2,FALSE) -> Celia Rouche | D49: =IF(E49="","No account",IFERROR(INDEX(account!$B:$B,MATCH(TRIM(CLEAN(E49)),account!$A:$A,0)),"Not Found")) -> retail | E49: =TRIM(CLEAN(I49)) -> Plexzap | F49: =VLOOKUP(Table1[[#This Row],[sales_agent]],'sales team'!A:C,3,FALSE) -> West | G49: =IF(E49="","No account",IFERROR(INDEX(account!$F:$F,MATCH(TRIM(CLEAN(E49)),account!$A:$A,0)),"Not Found")) -> United States | H49: GTX Basic | I49: Plexzap | J49: =IF(E49="","No account",IFERROR(INDEX(account!$D:$D,MATCH(TRIM(CLEAN(E49)),account!$A:$A,0)),"Not Found")) -> 2437.85 | K49: =IF(E49="","No account",IFERROR(INDEX(account!$E:$E,MATCH(TRIM(CLEAN(E49)),account!$A:$A,0)),"Not Found")) -> 4874 | L49: Lost | M49: 42690 | N49: 42805 | O49: 0 | P49: =IF(OR(M49="",N49=""),"N/A",IF(N49<M49,"ERROR","OK")) -> OK | Q49: =IF(Table1[[#This Row],[deal_stage]]="Won",1,0) -> 0 | R49: =IF(Table1[[#This Row],[deal_stage]] ="Lost",1,0) -> 1
A50: 0DFXFKT7 | B50: Darcel Schlecht | C50: =VLOOKUP(Table1[[#This Row],[sales_agent]],'sales team'!A:C,2,FALSE) -> Melvin Marxen | D50: =IF(E50="","No account",IFERROR(INDEX(account!$B:$B,MATCH(TRIM(CLEAN(E50)),account!$A:$A,0)),"Not Found")) -> technolgy | E50: =TRIM(CLEAN(I50)) -> Rundofase | F50: =VLOOKUP(Table1[[#This Row],[sales_agent]],'sales team'!A:C,3,FALSE) -> Central | G50: =IF(E50="","No account",IFERROR(INDEX(account!$F:$F,MATCH(TRIM(CLEAN(E50)),account!$A:$A,0)),"Not Found")) -> United States | H50: GTX Plus Basic | I50: Rundofase | J50: =IF(E50="","No account",IFERROR(INDEX(account!$D:$D,MATCH(TRIM(CLEAN(E50)),account!$A:$A,0)),"Not Found")) -> 1008.06 | K50: =IF(E50="","No account",IFERROR(INDEX(account!$E:$E,MATCH(TRIM(CLEAN(E50)),account!$A:$A,0)),"Not Found")) -> 1238 | L50: Lost | M50: 42691 | N50: 42815 | O50: 0 | P50: =IF(OR(M50="",N50=""),"N/A",IF(N50<M50,"ERROR","OK")) -> OK | Q50: =IF(Table1[[#This Row],[deal_stage]]="Won",1,0) -> 0 | R50: =IF(Table1[[#This Row],[deal_stage]] ="Lost",1,0) -> 1
A51: XKMZVSN4 | B51: James Ascencio | C51: =VLOOKUP(Table1[[#This Row],[sales_agent]],'sales team'!A:C,2,FALSE) -> Summer Sewald | D51: =IF(E51="","No account",IFERROR(INDEX(account!$B:$B,MATCH(TRIM(CLEAN(E51)),account!$A:$A,0)),"Not Found")) -> telecommunications | E51: =TRIM(CLEAN(I51)) -> Sonron | F51: =VLOOKUP(Table1[[#This Row],[sales_agent]],'sales team'!A:C,3,FALSE) -> West | G51: =IF(E51="","No account",IFERROR(INDEX(account!$F:$F,MATCH(TRIM(CLEAN(E51)),account!$A:$A,0)),"Not Found")) -> United States | H51: GTX Plus Pro | I51: Sonron | J51: =IF(E51="","No account",IFERROR(INDEX(account!$D:$D,MATCH(TRIM(CLEAN(E51)),account!$A:$A,0)),"Not Found")) -> 1699.85 | K51: =IF(E51="","No account",IFERROR(INDEX(account!$E:$E,MATCH(TRIM(CLEAN(E51)),account!$A:$A,0)),"Not Found")) -> 5108 | L51: Won | M51: 42691 | N51: 42799 | O51: 4667 | P51: =IF(OR(M51="",N51=""),"N/A",IF(N51<M51,"ERROR","OK")) -> OK | Q51: =IF(Table1[[#This Row],[deal_stage]]="Won",1,0) -> 1 | R51: =IF(Table1[[#This Row],[deal_stage]] ="Lost",1,0) -> 0
A52: IU8V0BZK | B52: Marty Freudenburg | C52: =VLOOKUP(Table1[[#This Row],[sales_agent]],'sales team'!A:C,2,FALSE) -> Melvin Marxen | D52: =IF(E52="","No account",IFERROR(INDEX(account!$B:$B,MATCH(TRIM(CLEAN(E52)),account!$A:$A,0)),"Not Found")) -> finance | E52: =TRIM(CLEAN(I52)) -> Finhigh | F52: =VLOOKUP(Table1[[#This Row],[sales_agent]],'sales team'!A:C,3,FALSE) -> Central | G52: =IF(E52="","No account",IFERROR(INDEX(account!$F:$F,MATCH(TRIM(CLEAN(E52)),account!$A:$A,0)),"Not Found")) -> United States | H52: GTX Plus Basic | I52: Finhigh | J52: =IF(E52="","No account",IFERROR(INDEX(account!$D:$D,MATCH(TRIM(CLEAN(E52)),account!$A:$A,0)),"Not Found")) -> 1102.43 | K52: =IF(E52="","No account",IFERROR(INDEX(account!$E:$E,MATCH(TRIM(CLEAN(E52)),account!$A:$A,0)),"Not Found")) -> 1759 | L52: Won | M52: 42691 | N52: 42811 | O52: 903 | P52: =IF(OR(M52="",N52=""),"N/A",IF(N52<M52,"ERROR","OK")) -> OK | Q52: =IF(Table1[[#This Row],[deal_stage]]="Won",1,0) -> 1 | R52: =IF(Table1[[#This Row],[deal_stage]] ="Lost",1,0) -> 0
A53: XY42936P | B53: Maureen Marcano | C53: =VLOOKUP(Table1[[#This Row],[sales_agent]],'sales team'!A:C,2,FALSE) -> Summer Sewald | D53: =IF(E53="","No account",IFERROR(INDEX(account!$B:$B,MATCH(TRIM(CLEAN(E53)),account!$A:$A,0)),"Not Found")) -> employment | E53: =TRIM(CLEAN(I53)) -> Finjob | F53: =VLOOKUP(Table1[[#This Row],[sales_agent]],'sales team'!A:C,3,FALSE) -> West | G53: =IF(E53="","No account",IFERROR(INDEX(account!$F:$F,MATCH(TRIM(CLEAN(E53)),account!$A:$A,0)),"Not Found")) -> United States | H53: GTX Plus Basic | I53: Finjob | J53: =IF(E53="","No account",IFERROR(INDEX(account!$D:$D,MATCH(TRIM(CLEAN(E53)),account!$A:$A,0)),"Not Found")) -> 2059.9 | K53: =IF(E53="","No account",IFERROR(INDEX(account!$E:$E,MATCH(TRIM(CLEAN(E53)),account!$A:$A,0)),"Not Found")) -> 3644 | L53: Won | M53: 42691 | N53: 42807 | O53: 1180 | P53: =IF(OR(M53="",N53=""),"N/A",IF(N53<M53,"ERROR","OK")) -> OK | Q53: =IF(Table1[[#This Row],[deal_stage]]="Won",1,0) -> 1 | R53: =IF(Table1[[#This Row],[deal_stage]] ="Lost",1,0) -> 0
A54: XRN54MBM | B54: Niesha Huffines | C54: =VLOOKUP(Table1[[#This Row],[sales_agent]],'sales team'!A:C,2,FALSE) -> Melvin Marxen | D54: =IF(E54="","No account",IFERROR(INDEX(account!$B:$B,MATCH(TRIM(CLEAN(E54)),account!$A:$A,0)),"Not Found")) -> medical | E54: =TRIM(CLEAN(I54)) -> Ron-tech | F54: =VLOOKUP(Table1[[#This Row],[sales_agent]],'sales team'!A:C,3,FALSE) -> Central | G54: =IF(E54="","No account",IFERROR(INDEX(account!$F:$F,MATCH(TRIM(CLEAN(E54)),account!$A:$A,0)),"Not Found")) -> United States | H54: GTX Basic | I54: Ron-tech | J54: =IF(E54="","No account",IFERROR(INDEX(account!$D:$D,MATCH(TRIM(CLEAN(E54)),account!$A:$A,0)),"Not Found")) -> 3922.42 | K54: =IF(E54="","No account",IFERROR(INDEX(account!$E:$E,MATCH(TRIM(CLEAN(E54)),account!$A:$A,0)),"Not Found")) -> 6837 | L54: Won | M54: 42691 | N54: 42799 | O54: 487 | P54: =IF(OR(M54="",N54=""),"N/A",IF(N54<M54,"ERROR","OK")) -> OK | Q54: =IF(Table1[[#This Row],[deal_stage]]="Won",1,0) -> 1 | R54: =IF(Table1[[#This Row],[deal_stage]] ="Lost",1,0) -> 0
A55: 2V848WZD | B55: Lajuana Vencill | C55: =VLOOKUP(Table1[[#This Row],[sales_agent]],'sales team'!A:C,2,FALSE) -> Dustin Brinkmann | D55: =IF(E55="","No account",IFERROR(INDEX(account!$B:$B,MATCH(TRIM(CLEAN(E55)),account!$A:$A,0)),"Not Found")) -> finance | E55: =TRIM(CLEAN(I55)) -> Stanredtax | F55: =VLOOKUP(Table1[[#This Row],[sales_agent]],'sales team'!A:C,3,FALSE) -> Central | G55: =IF(E55="","No account",IFERROR(INDEX(account!$F:$F,MATCH(TRIM(CLEAN(E55)),account!$A:$A,0)),"Not Found")) -> United States | H55: MG Advanced | I55: Stanredtax | J55: =IF(E55="","No account",IFERROR(INDEX(account!$D:$D,MATCH(TRIM(CLEAN(E55)),account!$A:$A,0)),"Not Found")) -> 1698.2 | K55: =IF(E55="","No account",IFERROR(INDEX(account!$E:$E,MATCH(TRIM(CLEAN(E55)),account!$A:$A,0)),"Not Found")) -> 3798 | L55: Won | M55: 42692 | N55: 42798 | O55: 3180 | P55: =IF(OR(M55="",N55=""),"N/A",IF(N55<M55,"ERROR","OK")) -> OK | Q55: =IF(Table1[[#This Row],[deal_stage]]="Won",1,0) -> 1 | R55: =IF(Table1[[#This Row],[deal_stage]] ="Lost",1,0) -> 0
A56: ONYNTUCG | B56: Darcel Schlecht | C56: =VLOOKUP(Table1[[#This Row],[sales_agent]],'sales team'!A:C,2,FALSE) -> Melvin Marxen | D56: =IF(E56="","No account",IFERROR(INDEX(account!$B:$B,MATCH(TRIM(CLEAN(E56)),account!$A:$A,0)),"Not Found")) -> finance | E56: =TRIM(CLEAN(I56)) -> Funholding | F56: =VLOOKUP(Table1[[#This Row],[sales_agent]],'sales team'!A:C,3,FALSE) -> Central | G56: =IF(E56="","No account",IFERROR(INDEX(account!$F:$F,MATCH(TRIM(CLEAN(E56)),account!$A:$A,0)),"Not Found")) -> United States | H56: GTXPro | I56: Funholding | J56: =IF(E56="","No account",IFERROR(INDEX(account!$D:$D,MATCH(TRIM(CLEAN(E56)),account!$A:$A,0)),"Not Found")) -> 2819.5 | K56: =IF(E56="","No account",IFERROR(INDEX(account!$E:$E,MATCH(TRIM(CLEAN(E56)),account!$A:$A,0)),"Not Found")) -> 7227 | L56: Lost | M56: 42693 | N56: 42811 | O56: 0 | P56: =IF(OR(M56="",N56=""),"N/A",IF(N56<M56,"ERROR","OK")) -> OK | Q56: =IF(Table1[[#This Row],[deal_stage]]="Won",1,0) -> 0 | R56: =IF(Table1[[#This Row],[deal_stage]] ="Lost",1,0) -> 1
A57: HIOHX80Y | B57: Darcel Schlecht | C57: =VLOOKUP(Table1[[#This Row],[sales_agent]],'sales team'!A:C,2,FALSE) -> Melvin Marxen | D57: =IF(E57="","No account",IFERROR(INDEX(account!$B:$B,MATCH(TRIM(CLEAN(E57)),account!$A:$A,0)),"Not Found")) -> telecommunications | E57: =TRIM(CLEAN(I57)) -> Gogozoom | F57: =VLOOKUP(Table1[[#This Row],[sales_agent]],'sales team'!A:C,3,FALSE) -> Central | G57: =IF(E57="","No account",IFERROR(INDEX(account!$F:$F,MATCH(TRIM(CLEAN(E57)),account!$A:$A,0)),"Not Found")) -> United States | H57: MG Advanced | I57: Gogozoom | J57: =IF(E57="","No account",IFERROR(INDEX(account!$D:$D,MATCH(TRIM(CLEAN(E57)),account!$A:$A,0)),"Not Found")) -> 86.68 | K57: =IF(E57="","No account",IFERROR(INDEX(account!$E:$E,MATCH(TRIM(CLEAN(E57)),account!$A:$A,0)),"Not Found")) -> 187 | L57: Won | M57: 42693 | N57: 42812 | O57: 3563 | P57: =IF(OR(M57="",N57=""),"N/A",IF(N57<M57,"ERROR","OK")) -> OK | Q57: =IF(Table1[[#This Row],[deal_stage]]="Won",1,0) -> 1 | R57: =IF(Table1[[#This Row],[deal_stage]] ="Lost",1,0) -> 0
A58: F5U1ACDD | B58: Kami Bicknell | C58: =VLOOKUP(Table1[[#This Row],[sales_agent]],'sales team'!A:C,2,FALSE) -> Summer Sewald | D58: =IF(E58="","No account",IFERROR(INDEX(account!$B:$B,MATCH(TRIM(CLEAN(E58)),account!$A:$A,0)),"Not Found")) -> No account | E58: =TRIM(CLEAN(I58)) | F58: =VLOOKUP(Table1[[#This Row],[sales_agent]],'sales team'!A:C,3,FALSE) -> West | G58: =IF(E58="","No account",IFERROR(INDEX(account!$F:$F,MATCH(TRIM(CLEAN(E58)),account!$A:$A,0)),"Not Found")) -> No account | H58: GTX Plus Basic | J58: =IF(E58="","No account",IFERROR(INDEX(account!$D:$D,MATCH(TRIM(CLEAN(E58)),account!$A:$A,0)),"Not Found")) -> No account | K58: =IF(E58="","No account",IFERROR(INDEX(account!$E:$E,MATCH(TRIM(CLEAN(E58)),account!$A:$A,0)),"Not Found")) -> No account | L58: Engaging | M58: 42693 | P58: =IF(OR(M58="",N58=""),"N/A",IF(N58<M58,"ERROR","OK")) -> N/A | Q58: =IF(Table1[[#This Row],[deal_stage]]="Won",1,0) -> 0 | R58: =IF(Table1[[#This Row],[deal_stage]] ="Lost",1,0) -> 0
A59: LPKT07PV | B59: Boris Faz | C59: =VLOOKUP(Table1[[#This Row],[sales_agent]],'sales team'!A:C,2,FALSE) -> Rocco Neubert | D59: =IF(E59="","No account",IFERROR(INDEX(account!$B:$B,MATCH(TRIM(CLEAN(E59)),account!$A:$A,0)),"Not Found")) -> finance | E59: =TRIM(CLEAN(I59)) -> Opentech | F59: =VLOOKUP(Table1[[#This Row],[sales_agent]],'sales team'!A:C,3,FALSE) -> East | G59: =IF(E59="","No account",IFERROR(INDEX(account!$F:$F,MATCH(TRIM(CLEAN(E59)),account!$A:$A,0)),"Not Found")) -> United States | H59: GTXPro | I59: Opentech | J59: =IF(E59="","No account",IFERROR(INDEX(account!$D:$D,MATCH(TRIM(CLEAN(E59)),account!$A:$A,0)),"Not Found")) -> 355.23 | K59: =IF(E59="","No account",IFERROR(INDEX(account!$E:$E,MATCH(TRIM(CLEAN(E59)),account!$A:$A,0)),"Not Found")) -> 853 | L59: Won | M59: 42694 | N59: 42817 | O59: 4704 | P59: =IF(OR(M59="",N59=""),"N/A",IF(N59<M59,"ERROR","OK")) -> OK | Q59: =IF(Table1[[#This Row],[deal_stage]]="Won",1,0) -> 1 | R59: =IF(Table1[[#This Row],[deal_stage]] ="Lost",1,0) -> 0
A60: WPB2SLIG | B60: Donn Cantrell | C60: =VLOOKUP(Table1[[#This Row],[sales_agent]],'sales team'!A:C,2,FALSE) -> Rocco Neubert | D60: =IF(E60="","No account",IFERROR(INDEX(account!$B:$B,MATCH(TRIM(CLEAN(E60)),account!$A:$A,0)),"Not Found")) -> medical | E60: =TRIM(CLEAN(I60)) -> Silis | F60: =VLOOKUP(Table1[[#This Row],[sales_agent]],'sales team'!A:C,3,FALSE) -> East | G60: =IF(E60="","No account",IFERROR(INDEX(account!$F:$F,MATCH(TRIM(CLEAN(E60)),account!$A:$A,0)),"Not Found")) -> United States | H60: GTX Plus Pro | I60: Silis | J60: =IF(E60="","No account",IFERROR(INDEX(account!$D:$D,MATCH(TRIM(CLEAN(E60)),account!$A:$A,0)),"Not Found")) -> 2818.38 | K60: =IF(E60="","No account",IFERROR(INDEX(account!$E:$E,MATCH(TRIM(CLEAN(E60)),account!$A:$A,0)),"Not Found")) -> 6290 | L60: Won | M60: 42694 | N60: 42808 | O60: 5585 | P60: =IF(OR(M60="",N60=""),"N/A",IF(N60<M60,"ERROR","OK")) -> OK | Q60: =IF(Table1[[#This Row],[deal_stage]]="Won",1,0) -> 1 | R60: =IF(Table1[[#This Row],[deal_stage]] ="Lost",1,0) -> 0
A61: XUSUEAV7 | B61: Elease Gluck | C61: =VLOOKUP(Table1[[#This Row],[sales_agent]],'sales team'!A:C,2,FALSE) -> Celia Rouche | D61: =IF(E61="","No account",IFERROR(INDEX(account!$B:$B,MATCH(TRIM(CLEAN(E61)),account!$A:$A,0)),"Not Found")) -> entertainment | E61: =TRIM(CLEAN(I61)) -> Zoomit | F61: =VLOOKUP(Table1[[#This Row],[sales_agent]],'sales team'!A:C,3,FALSE) -> West | G61: =IF(E61="","No account",IFERROR(INDEX(account!$F:$F,MATCH(TRIM(CLEAN(E61)),account!$A:$A,0)),"Not Found")) -> United States | H61: GTK 500 | I61: Zoomit | J61: =IF(E61="","No account",IFERROR(INDEX(account!$D:$D,MATCH(TRIM(CLEAN(E61)),account!$A:$A,0)),"Not Found")) -> 324.19 | K61: =IF(E61="","No account",IFERROR(INDEX(account!$E:$E,MATCH(TRIM(CLEAN(E61)),account!$A:$A,0)),"Not Found")) -> 978 | L61: Won | M61: 42694 | N61: 42803 | O61: 25897 | P61: =IF(OR(M61="",N61=""),"N/A",IF(N61<M61,"ERROR","OK")) -> OK | Q61: =IF(Table1[[#This Row],[deal_stage]]="Won",1,0) -> 1 | R61: =IF(Table1[[#This Row],[deal_stage]] ="Lost",1,0) -> 0
A62: ZZY4516R | B62: Hayden Neloms | C62: =VLOOKUP(Table1[[#This Row],[sales_agent]],'sales team'!A:C,2,FALSE) -> Celia Rouche | D62: =IF(E62="","No account",IFERROR(INDEX(account!$B:$B,MATCH(TRIM(CLEAN(E62)),account!$A:$A,0)),"Not Found")) -> No account | E62: =TRIM(CLEAN(I62)) | F62: =VLOOKUP(Table1[[#This Row],[sales_agent]],'sales team'!A:C,3,FALSE) -> West | G62: =IF(E62="","No account",IFERROR(INDEX(account!$F:$F,MATCH(TRIM(CLEAN(E62)),account!$A:$A,0)),"Not Found")) -> No account | H62: MG Advanced | J62: =IF(E62="","No account",IFERROR(INDEX(account!$D:$D,MATCH(TRIM(CLEAN(E62)),account!$A:$A,0)),"Not Found")) -> No account | K62: =IF(E62="","No account",IFERROR(INDEX(account!$E:$E,MATCH(TRIM(CLEAN(E62)),account!$A:$A,0)),"Not Found")) -> No account | L62: Engaging | M62: 42694 | P62: =IF(OR(M62="",N62=""),"N/A",IF(N62<M62,"ERROR","OK")) -> N/A | Q62: =IF(Table1[[#This Row],[deal_stage]]="Won",1,0) -> 0 | R62: =IF(Table1[[#This Row],[deal_stage]] ="Lost",1,0) -> 0
A63: 3TYPII47 | B63: Kami Bicknell | C63: =VLOOKUP(Table1[[#This Row],[sales_agent]],'sales team'!A:C,2,FALSE) -> Summer Sewald | D63: =IF(E63="","No account",IFERROR(INDEX(account!$B:$B,MATCH(TRIM(CLEAN(E63)),account!$A:$A,0)),"Not Found")) -> marketing | E63: =TRIM(CLEAN(I63)) -> Goodsilron | F63: =VLOOKUP(Table1[[#This Row],[sales_agent]],'sales team'!A:C,3,FALSE) -> West | G63: =IF(E63="","No account",IFERROR(INDEX(account!$F:$F,MATCH(TRIM(CLEAN(E63)),account!$A:$A,0)),"Not Found")) -> United States | H63: GTX Plus Basic | I63: Goodsilron | J63: =IF(E63="","No account",IFERROR(INDEX(account!$D:$D,MATCH(TRIM(CLEAN(E63)),account!$A:$A,0)),"Not Found")) -> 2952.73 | K63: =IF(E63="","No account",IFERROR(INDEX(account!$E:$E,MATCH(TRIM(CLEAN(E63)),account!$A:$A,0)),"Not Found")) -> 5107 | L63: Won | M63: 42694 | N63: 42797 | O63: 1207 | P63: =IF(OR(M63="",N63=""),"N/A",IF(N63<M63,"ERROR","OK")) -> OK | Q63: =IF(Table1[[#This Row],[deal_stage]]="Won",1,0) -> 1 | R63: =IF(Table1[[#This Row],[deal_stage]] ="Lost",1,0) -> 0
A64: 7WAX8Z8O | B64: Lajuana Vencill | C64: =VLOOKUP(Table1[[#This Row],[sales_agent]],'sales team'!A:C,2,FALSE) -> Dustin Brinkmann | D64: =IF(E64="","No account",IFERROR(INDEX(account!$B:$B,MATCH(TRIM(CLEAN(E64)),account!$A:$A,0)),"Not Found")) -> retail | E64: =TRIM(CLEAN(I64)) -> Cancity | F64: =VLOOKUP(Table1[[#This Row],[sales_agent]],'sales team'!A:C,3,FALSE) -> Central | G64: =IF(E64="","No account",IFERROR(INDEX(account!$F:$F,MATCH(TRIM(CLEAN(E64)),account!$A:$A,0)),"Not Found")) -> United States | H64: MG Advanced | I64: Cancity | J64: =IF(E64="","No account",IFERROR(INDEX(account!$D:$D,MATCH(TRIM(CLEAN(E64)),account!$A:$A,0)),"Not Found")) -> 718.62 | K64: =IF(E64="","No account",IFERROR(INDEX(account!$E:$E,MATCH(TRIM(CLEAN(E64)),account!$A:$A,0)),"Not Found")) -> 2448 | L64: Lost | M64: 42694 | N64: 42802 | O64: 0 | P64: =IF(OR(M64="",N64=""),"N/A",IF(N64<M64,"ERROR","OK")) -> OK | Q64: =IF(Table1[[#This Row],[deal_stage]]="Won",1,0) -> 0 | R64: =IF(Table1[[#This Row],[deal_stage]] ="Lost",1,0) -> 1
A65: MYDUMR3R | B65: Lajuana Vencill | C65: =VLOOKUP(Table1[[#This Row],[sales_agent]],'sales team'!A:C,2,FALSE) -> Dustin Brinkmann | D65: =IF(E65="","No account",IFERROR(INDEX(account!$B:$B,MATCH(TRIM(CLEAN(E65)),account!$A:$A,0)),"Not Found")) -> technolgy | E65: =TRIM(CLEAN(I65)) -> Rangreen | F65: =VLOOKUP(Table1[[#This Row],[sales_agent]],'sales team'!A:C,3,FALSE) -> Central | G65: =IF(E65="","No account",IFERROR(INDEX(account!$F:$F,MATCH(TRIM(CLEAN(E65)),account!$A:$A,0)),"Not Found")) -> Panama | H65: GTX Basic | I65: Rangreen | J65: =IF(E65="","No account",IFERROR(INDEX(account!$D:$D,MATCH(TRIM(CLEAN(E65)),account!$A:$A,0)),"Not Found")) -> 2938.67 | K65: =IF(E65="","No account",IFERROR(INDEX(account!$E:$E,MATCH(TRIM(CLEAN(E65)),account!$A:$A,0)),"Not Found")) -> 8775 | L65: Won | M65: 42694 | N65: 42798 | O65: 559 | P65: =IF(OR(M65="",N65=""),"N/A",IF(N65<M65,"ERROR","OK")) -> OK | Q65: =IF(Table1[[#This Row],[deal_stage]]="Won",1,0) -> 1 | R65: =IF(Table1[[#This Row],[deal_stage]] ="Lost",1,0) -> 0
A66: 0DRC1U9Q | B66: Maureen Marcano | C66: =VLOOKUP(Table1[[#This Row],[sales_agent]],'sales team'!A:C,2,FALSE) -> Summer Sewald | D66: =IF(E66="","No account",IFERROR(INDEX(account!$B:$B,MATCH(TRIM(CLEAN(E66)),account!$A:$A,0)),"Not Found")) -> services | E66: =TRIM(CLEAN(I66)) -> Green-Plus | F66: =VLOOKUP(Table1[[#This Row],[sales_agent]],'sales team'!A:C,3,FALSE) -> West | G66: =IF(E66="","No account",IFERROR(INDEX(account!$F:$F,MATCH(TRIM(CLEAN(E66)),account!$A:$A,0)),"Not Found")) -> United States | H66: GTX Basic | I66: Green-Plus | J66: =IF(E66="","No account",IFERROR(INDEX(account!$D:$D,MATCH(TRIM(CLEAN(E66)),account!$A:$A,0)),"Not Found")) -> 692.19 | K66: =IF(E66="","No account",IFERROR(INDEX(account!$E:$E,MATCH(TRIM(CLEAN(E66)),account!$A:$A,0)),"Not Found")) -> 1922 | L66: Engaging | M66: 42694 | P66: =IF(OR(M66="",N66=""),"N/A",IF(N66<M66,"ERROR","OK")) -> N/A | Q66: =IF(Table1[[#This Row],[deal_stage]]="Won",1,0) -> 0 | R66: =IF(Table1[[#This Row],[deal_stage]] ="Lost",1,0) -> 0
A67: 37JFKD4I | B67: Niesha Huffines | C67: =VLOOKUP(Table1[[#This Row],[sales_agent]],'sales team'!A:C,2,FALSE) -> Melvin Marxen | D67: =IF(E67="","No account",IFERROR(INDEX(account!$B:$B,MATCH(TRIM(CLEAN(E67)),account!$A:$A,0)),"Not Found")) -> marketing | E67: =TRIM(CLEAN(I67)) -> dambase | F67: =VLOOKUP(Table1[[#This Row],[sales_agent]],'sales team'!A:C,3,FALSE) -> Central | G67: =IF(E67="","No account",IFERROR(INDEX(account!$F:$F,MATCH(TRIM(CLEAN(E67)),account!$A:$A,0)),"Not Found")) -> United States | H67: GTX Plus Basic | I67: dambase | J67: =IF(E67="","No account",IFERROR(INDEX(account!$D:$D,MATCH(TRIM(CLEAN(E67)),account!$A:$A,0)),"Not Found")) -> 2173.98 | K67: =IF(E67="","No account",IFERROR(INDEX(account!$E:$E,MATCH(TRIM(CLEAN(E67)),account!$A:$A,0)),"Not Found")) -> 2928 | L67: Won | M67: 42694 | N67: 42803 | O67: 1033 | P67: =IF(OR(M67="",N67=""),"N/A",IF(N67<M67,"ERROR","OK")) -> OK | Q67: =IF(Table1[[#This Row],[deal_stage]]="Won",1,0) -> 1 | R67: =IF(Table1[[#This Row],[deal_stage]] ="Lost",1,0) -> 0
A68: 25YKPHX8 | B68: Donn Cantrell | C68: =VLOOKUP(Table1[[#This Row],[sales_agent]],'sales team'!A:C,2,FALSE) -> Rocco Neubert | D68: =IF(E68="","No account",IFERROR(INDEX(account!$B:$B,MATCH(TRIM(CLEAN(E68)),account!$A:$A,0)),"Not Found")) -> software | E68: =TRIM(CLEAN(I68)) -> Kan-code | F68: =VLOOKUP(Table1[[#This Row],[sales_agent]],'sales team'!A:C,3,FALSE) -> East | G68: =IF(E68="","No account",IFERROR(INDEX(account!$F:$F,MATCH(TRIM(CLEAN(E68)),account!$A:$A,0)),"Not Found")) -> United States | H68: GTX Basic | I68: Kan-code | J68: =IF(E68="","No account",IFERROR(INDEX(account!$D:$D,MATCH(TRIM(CLEAN(E68)),account!$A:$A,0)),"Not Found")) -> 11698.03 | K68: =IF(E68="","No account",IFERROR(INDEX(account!$E:$E,MATCH(TRIM(CLEAN(E68)),account!$A:$A,0)),"Not Found")) -> 34288 | L68: Won | M68: 42695 | N68: 42815 | O68: 462 | P68: =IF(OR(M68="",N68=""),"N/A",IF(N68<M68,"ERROR","OK")) -> OK | Q68: =IF(Table1[[#This Row],[deal_stage]]="Won",1,0) -> 1 | R68: =IF(Table1[[#This Row],[deal_stage]] ="Lost",1,0) -> 0
A69: BXXMA7F3 | B69: Hayden Neloms | C69: =VLOOKUP(Table1[[#This Row],[sales_agent]],'sales team'!A:C,2,FALSE) -> Celia Rouche | D69: =IF(E69="","No account",IFERROR(INDEX(account!$B:$B,MATCH(TRIM(CLEAN(E69)),account!$A:$A,0)),"Not Found")) -> services | E69: =TRIM(CLEAN(I69)) -> Nam-zim | F69: =VLOOKUP(Table1[[#This Row],[sales_agent]],'sales team'!A:C,3,FALSE) -> West | G69: =IF(E69="","No account",IFERROR(INDEX(account!$F:$F,MATCH(TRIM(CLEAN(E69)),account!$A:$A,0)),"Not Found")) -> Brazil | H69: MG Advanced | I69: Nam-zim | J69: =IF(E69="","No account",IFERROR(INDEX(account!$D:$D,MATCH(TRIM(CLEAN(E69)),account!$A:$A,0)),"Not Found")) -> 405.59 | K69: =IF(E69="","No account",IFERROR(INDEX(account!$E:$E,MATCH(TRIM(CLEAN(E69)),account!$A:$A,0)),"Not Found")) -> 1179 | L69: Lost | M69: 42695 | N69: 42795 | O69: 0 | P69: =IF(OR(M69="",N69=""),"N/A",IF(N69<M69,"ERROR","OK")) -> OK | Q69: =IF(Table1[[#This Row],[deal_stage]]="Won",1,0) -> 0 | R69: =IF(Table1[[#This Row],[deal_stage]] ="Lost",1,0) -> 1
A70: GIUUTBXM | B70: Kary Hendrixson | C70: =VLOOKUP(Table1[[#This Row],[sales_agent]],'sales team'!A:C,2,FALSE) -> Summer Sewald | D70: =IF(E70="","No account",IFERROR(INDEX(account!$B:$B,MATCH(TRIM(CLEAN(E70)),account!$A:$A,0)),"Not Found")) -> employment | E70: =TRIM(CLEAN(I70)) -> Y-corporation | F70: =VLOOKUP(Table1[[#This Row],[sales_agent]],'sales team'!A:C,3,FALSE) -> West | G70: =IF(E70="","No account",IFERROR(INDEX(account!$F:$F,MATCH(TRIM(CLEAN(E70)),account!$A:$A,0)),"Not Found")) -> United States | H70: GTXPro | I70: Y-corporation | J70: =IF(E70="","No account",IFERROR(INDEX(account!$D:$D,MATCH(TRIM(CLEAN(E70)),account!$A:$A,0)),"Not Found")) -> 2871.35 | K70: =IF(E70="","No account",IFERROR(INDEX(account!$E:$E,MATCH(TRIM(CLEAN(E70)),account!$A:$A,0)),"Not Found")) -> 9561 | L70: Won | M70: 42695 | N70: 42808 | O70: 5539 | P70: =IF(OR(M70="",N70=""),"N/A",IF(N70<M70,"ERROR","OK")) -> OK | Q70: =IF(Table1[[#This Row],[deal_stage]]="Won",1,0) -> 1 | R70: =IF(Table1[[#This Row],[deal_stage]] ="Lost",1,0) -> 0
A71: MFX2LR1Q | B71: Lajuana Vencill | C71: =VLOOKUP(Table1[[#This Row],[sales_agent]],'sales team'!A:C,2,FALSE) -> Dustin Brinkmann | D71: =IF(E71="","No account",IFERROR(INDEX(account!$B:$B,MATCH(TRIM(CLEAN(E71)),account!$A:$A,0)),"Not Found")) -> medical | E71: =TRIM(CLEAN(I71)) -> Ron-tech | F71: =VLOOKUP(Table1[[#This Row],[sales_agent]],'sales team'!A:C,3,FALSE) -> Central | G71: =IF(E71="","No account",IFERROR(INDEX(account!$F:$F,MATCH(TRIM(CLEAN(E71)),account!$A:$A,0)),"Not Found")) -> United States | H71: MG Advanced | I71: Ron-tech | J71: =IF(E71="","No account",IFERROR(INDEX(account!$D:$D,MATCH(TRIM(CLEAN(E71)),account!$A:$A,0)),"Not Found")) -> 3922.42 | K71: =IF(E71="","No account",IFERROR(INDEX(account!$E:$E,MATCH(TRIM(CLEAN(E71)),account!$A:$A,0)),"Not Found")) -> 6837 | L71: Won | M71: 42695 | N71: 42809 | O71: 3573 | P71: =IF(OR(M71="",N71=""),"N/A",IF(N71<M71,"ERROR","OK")) -> OK | Q71: =IF(Table1[[#This Row],[deal_stage]]="Won",1,0) -> 1 | R71: =IF(Table1[[#This Row],[deal_stage]] ="Lost",1,0) -> 0
A72: DUHE9FLY | B72: Marty Freudenburg | C72: =VLOOKUP(Table1[[#This Row],[sales_agent]],'sales team'!A:C,2,FALSE) -> Melvin Marxen | D72: =IF(E72="","No account",IFERROR(INDEX(account!$B:$B,MATCH(TRIM(CLEAN(E72)),account!$A:$A,0)),"Not Found")) -> technolgy | E72: =TRIM(CLEAN(I72)) -> Conecom | F72: =VLOOKUP(Table1[[#This Row],[sales_agent]],'sales team'!A:C,3,FALSE) -> Central | G72: =IF(E72="","No account",IFERROR(INDEX(account!$F:$F,MATCH(TRIM(CLEAN(E72)),account!$A:$A,0)),"Not Found")) -> United States | H72: GTXPro | I72: Conecom | J72: =IF(E72="","No account",IFERROR(INDEX(account!$D:$D,MATCH(TRIM(CLEAN(E72)),account!$A:$A,0)),"Not Found")) -> 1520.66 | K72: =IF(E72="","No account",IFERROR(INDEX(account!$E:$E,MATCH(TRIM(CLEAN(E72)),account!$A:$A,0)),"Not Found")) -> 1806 | L72: Won | M72: 42695 | N72: 42795 | O72: 4926 | P72: =IF(OR(M72="",N72=""),"N/A",IF(N72<M72,"ERROR","OK")) -> OK | Q72: =IF(Table1[[#This Row],[deal_stage]]="Won",1,0) -> 1 | R72: =IF(Table1[[#This Row],[deal_stage]] ="Lost",1,0) -> 0
A73: 96BSG7R1 | B73: Zane Levy | C73: =VLOOKUP(Table1[[#This Row],[sales_agent]],'sales team'!A:C,2,FALSE) -> Summer Sewald | D73: =IF(E73="","No account",IFERROR(INDEX(account!$B:$B,MATCH(TRIM(CLEAN(E73)),account!$A:$A,0)),"Not Found")) -> marketing | E73: =TRIM(CLEAN(I73)) -> Sunnamplex | F73: =VLOOKUP(Table1[[#This Row],[sales_agent]],'sales team'!A:C,3,FALSE) -> West | G73: =IF(E73="","No account",IFERROR(INDEX(account!$F:$F,MATCH(TRIM(CLEAN(E73)),account!$A:$A,0)),"Not Found")) -> Poland | H73: GTX Plus Basic | I73: Sunnamplex | J73: =IF(E73="","No account",IFERROR(INDEX(account!$D:$D,MATCH(TRIM(CLEAN(E73)),account!$A:$A,0)),"Not Found")) -> 894.37 | K73: =IF(E73="","No account",IFERROR(INDEX(account!$E:$E,MATCH(TRIM(CLEAN(E73)),account!$A:$A,0)),"Not Found")) -> 1593 | L73: Lost | M73: 42695 | N73: 42811 | O73: 0 | P73: =IF(OR(M73="",N73=""),"N/A",IF(N73<M73,"ERROR","OK")) -> OK | Q73: =IF(Table1[[#This Row],[deal_stage]]="Won",1,0) -> 0 | R73: =IF(Table1[[#This Row],[deal_stage]] ="Lost",1,0) -> 1
A74: 7FQMSWIX | B74: Corliss Cosme | C74: =VLOOKUP(Table1[[#This Row],[sales_agent]],'sales team'!A:C,2,FALSE) -> Cara Losch | D74: =IF(E74="","No account",IFERROR(INDEX(account!$B:$B,MATCH(TRIM(CLEAN(E74)),account!$A:$A,0)),"Not Found")) -> medical | E74: =TRIM(CLEAN(I74)) -> Bioplex | F74: =VLOOKUP(Table1[[#This Row],[sales_agent]],'sales team'!A:C,3,FALSE) -> East | G74: =IF(E74="","No account",IFERROR(INDEX(account!$F:$F,MATCH(TRIM(CLEAN(E74)),account!$A:$A,0)),"Not Found")) -> United States | H74: MG Special | I74: Bioplex | J74: =IF(E74="","No account",IFERROR(INDEX(account!$D:$D,MATCH(TRIM(CLEAN(E74)),account!$A:$A,0)),"Not Found")) -> 326.82 | K74: =IF(E74="","No account",IFERROR(INDEX(account!$E:$E,MATCH(TRIM(CLEAN(E74)),account!$A:$A,0)),"Not Found")) -> 1016 | L74: Won | M74: 42696 | N74: 42798 | O74: 62 | P74: =IF(OR(M74="",N74=""),"N/A",IF(N74<M74,"ERROR","OK")) -> OK | Q74: =IF(Table1[[#This Row],[deal_stage]]="Won",1,0) -> 1 | R74: =IF(Table1[[#This Row],[deal_stage]] ="Lost",1,0) -> 0
A75: C20AVXN7 | B75: Darcel Schlecht | C75: =VLOOKUP(Table1[[#This Row],[sales_agent]],'sales team'!A:C,2,FALSE) -> Melvin Marxen | D75: =IF(E75="","No account",IFERROR(INDEX(account!$B:$B,MATCH(TRIM(CLEAN(E75)),account!$A:$A,0)),"Not Found")) -> telecommunications | E75: =TRIM(CLEAN(I75)) -> Gogozoom | F75: =VLOOKUP(Table1[[#This Row],[sales_agent]],'sales team'!A:C,3,FALSE) -> Central | G75: =IF(E75="","No account",IFERROR(INDEX(account!$F:$F,MATCH(TRIM(CLEAN(E75)),account!$A:$A,0)),"Not Found")) -> United States | H75: GTXPro | I75: Gogozoom | J75: =IF(E75="","No account",IFERROR(INDEX(account!$D:$D,MATCH(TRIM(CLEAN(E75)),account!$A:$A,0)),"Not Found")) -> 86.68 | K75: =IF(E75="","No account",IFERROR(INDEX(account!$E:$E,MATCH(TRIM(CLEAN(E75)),account!$A:$A,0)),"Not Found")) -> 187 | L75: Won | M75: 42696 | N75: 42808 | O75: 4359 | P75: =IF(OR(M75="",N75=""),"N/A",IF(N75<M75,"ERROR","OK")) -> OK | Q75: =IF(Table1[[#This Row],[deal_stage]]="Won",1,0) -> 1 | R75: =IF(Table1[[#This Row],[deal_stage]] ="Lost",1,0) -> 0
A76: GS1QVWCR | B76: Kami Bicknell | C76: =VLOOKUP(Table1[[#This Row],[sales_agent]],'sales team'!A:C,2,FALSE) -> Summer Sewald | D76: =IF(E76="","No account",IFERROR(INDEX(account!$B:$B,MATCH(TRIM(CLEAN(E76)),account!$A:$A,0)),"Not Found")) -> entertainment | E76: =TRIM(CLEAN(I76)) -> Plusstrip | F76: =VLOOKUP(Table1[[#This Row],[sales_agent]],'sales team'!A:C,3,FALSE) -> West | G76: =IF(E76="","No account",IFERROR(INDEX(account!$F:$F,MATCH(TRIM(CLEAN(E76)),account!$A:$A,0)),"Not Found")) -> United States | H76: GTX Basic | I76: Plusstrip | J76: =IF(E76="","No account",IFERROR(INDEX(account!$D:$D,MATCH(TRIM(CLEAN(E76)),account!$A:$A,0)),"Not Found")) -> 349.81 | K76: =IF(E76="","No account",IFERROR(INDEX(account!$E:$E,MATCH(TRIM(CLEAN(E76)),account!$A:$A,0)),"Not Found")) -> 315 | L76: Won | M76: 42696 | N76: 42825 | O76: 566 | P76: =IF(OR(M76="",N76=""),"N/A",IF(N76<M76,"ERROR","OK")) -> OK | Q76: =IF(Table1[[#This Row],[deal_stage]]="Won",1,0) -> 1 | R76: =IF(Table1[[#This Row],[deal_stage]] ="Lost",1,0) -> 0
A77: ZWH8FXY3 | B77: Marty Freudenburg | C77: =VLOOKUP(Table1[[#This Row],[sales_agent]],'sales team'!A:C,2,FALSE) -> Melvin Marxen | D77: =IF(E77="","No account",IFERROR(INDEX(account!$B:$B,MATCH(TRIM(CLEAN(E77)),account!$A:$A,0)),"Not Found")) -> retail | E77: =TRIM(CLEAN(I77)) -> Toughzap | F77: =VLOOKUP(Table1[[#This Row],[sales_agent]],'sales team'!A:C,3,FALSE) -> Central | G77: =IF(E77="","No account",IFERROR(INDEX(account!$F:$F,MATCH(TRIM(CLEAN(E77)),account!$A:$A,0)),"Not Found")) -> United States | H77: GTX Basic | I77: Toughzap | J77: =IF(E77="","No account",IFERROR(INDEX(account!$D:$D,MATCH(TRIM(CLEAN(E77)),account!$A:$A,0)),"Not Found")) -> 332.43 | K77: =IF(E77="","No account",IFERROR(INDEX(account!$E:$E,MATCH(TRIM(CLEAN(E77)),account!$A:$A,0)),"Not Found")) -> 799 | L77: Won | M77: 42696 | N77: 42797 | O77: 508 | P77: =IF(OR(M77="",N77=""),"N/A",IF(N77<M77,"ERROR","OK")) -> OK | Q77: =IF(Table1[[#This Row],[deal_stage]]="Won",1,0) -> 1 | R77: =IF(Table1[[#This Row],[deal_stage]] ="Lost",1,0) -> 0
A78: 2U94Y3Q9 | B78: Rosie Papadopoulos | C78: =VLOOKUP(Table1[[#This Row],[sales_agent]],'sales team'!A:C,2,FALSE) -> Cara Losch | D78: =IF(E78="","No account",IFERROR(INDEX(account!$B:$B,MATCH(TRIM(CLEAN(E78)),account!$A:$A,0)),"Not Found")) -> finance | E78: =TRIM(CLEAN(I78)) -> Vehement Capital Partners | F78: =VLOOKUP(Table1[[#This Row],[sales_agent]],'sales team'!A:C,3,FALSE) -> East | G78: =IF(E78="","No account",IFERROR(INDEX(account!$F:$F,MATCH(TRIM(CLEAN(E78)),account!$A:$A,0)),"Not Found")) -> United States | H78: MG Advanced | I78: Vehement Capital Partners | J78: =IF(E78="","No account",IFERROR(INDEX(account!$D:$D,MATCH(TRIM(CLEAN(E78)),account!$A:$A,0)),"Not Found")) -> 646.1 | K78: =IF(E78="","No account",IFERROR(INDEX(account!$E:$E,MATCH(TRIM(CLEAN(E78)),account!$A:$A,0)),"Not Found")) -> 883 | L78: Lost | M78: 42696 | N78: 42814 | O78: 0 | P78: =IF(OR(M78="",N78=""),"N/A",IF(N78<M78,"ERROR","OK")) -> OK | Q78: =IF(Table1[[#This Row],[deal_stage]]="Won",1,0) -> 0 | R78: =IF(Table1[[#This Row],[deal_stage]] ="Lost",1,0) -> 1
... A80: B6B0PNR2 | B80: Vicki Laflamme | C80: =VLOOKUP(Table1[[#This Row],[sales_agent]],'sales team'!A:C,2,FALSE) -> Celia Rouche | D80: =IF(E80="","No account",IFERROR(INDEX(account!$B:$B,MATCH(TRIM(CLEAN(E80)),account!$A:$A,0)),"Not Found")) -> software | E80: =TRIM(CLEAN(I80)) -> Dalttechnology | F80: =VLOOKUP(Table1[[#This Row],[sales_agent]],'sales team'!A:C,3,FALSE) -> West | G80: =IF(E80="","No account",IFERROR(INDEX(account!$F:$F,MATCH(TRIM(CLEAN(E80)),account!$A:$A,0)),"Not Found")) -> United States | H80: GTXPro | I80: Dalttechnology | J80: =IF(E80="","No account",IFERROR(INDEX(account!$D:$D,MATCH(TRIM(CLEAN(E80)),account!$A:$A,0)),"Not Found")) -> 98.79 | K80: =IF(E80="","No account",IFERROR(INDEX(account!$E:$E,MATCH(TRIM(CLEAN(E80)),account!$A:$A,0)),"Not Found")) -> 96 | L80: Won | M80: 42696 | N80: 42799 | O80: 4899 | P80: =IF(OR(M80="",N80=""),"N/A",IF(N80<M80,"ERROR","OK")) -> OK | Q80: =IF(Table1[[#This Row],[deal_stage]]="Won",1,0) -> 1 | R80: =IF(Table1[[#This Row],[deal_stage]] ="Lost",1,0) -> 0
A81: M7I5O9YU | B81: Corliss Cosme | C81: =VLOOKUP(Table1[[#This Row],[sales_agent]],'sales team'!A:C,2,FALSE) -> Cara Losch | D81: =IF(E81="","No account",IFERROR(INDEX(account!$B:$B,MATCH(TRIM(CLEAN(E81)),account!$A:$A,0)),"Not Found")) -> entertainment | E81: =TRIM(CLEAN(I81)) -> Cheers | F81: =VLOOKUP(Table1[[#This Row],[sales_agent]],'sales team'!A:C,3,FALSE) -> East | G81: =IF(E81="","No account",IFERROR(INDEX(account!$F:$F,MATCH(TRIM(CLEAN(E81)),account!$A:$A,0)),"Not Found")) -> United States | H81: GTX Basic | I81: Cheers | J81: =IF(E81="","No account",IFERROR(INDEX(account!$D:$D,MATCH(TRIM(CLEAN(E81)),account!$A:$A,0)),"Not Found")) -> 4269.9 | K81: =IF(E81="","No account",IFERROR(INDEX(account!$E:$E,MATCH(TRIM(CLEAN(E81)),account!$A:$A,0)),"Not Found")) -> 6472 | L81: Engaging | M81: 42697 | P81: =IF(OR(M81="",N81=""),"N/A",IF(N81<M81,"ERROR","OK")) -> N/A | Q81: =IF(Table1[[#This Row],[deal_stage]]="Won",1,0) -> 0 | R81: =IF(Table1[[#This Row],[deal_stage]] ="Lost",1,0) -> 0
A82: LXZA2OSZ | B82: Corliss Cosme | C82: =VLOOKUP(Table1[[#This Row],[sales_agent]],'sales team'!A:C,2,FALSE) -> Cara Losch | D82: =IF(E82="","No account",IFERROR(INDEX(account!$B:$B,MATCH(TRIM(CLEAN(E82)),account!$A:$A,0)),"Not Found")) -> employment | E82: =TRIM(CLEAN(I82)) -> Ontomedia | F82: =VLOOKUP(Table1[[#This Row],[sales_agent]],'sales team'!A:C,3,FALSE) -> East | G82: =IF(E82="","No account",IFERROR(INDEX(account!$F:$F,MATCH(TRIM(CLEAN(E82)),account!$A:$A,0)),"Not Found")) -> United States | H82: GTX Plus Pro | I82: Ontomedia | J82: =IF(E82="","No account",IFERROR(INDEX(account!$D:$D,MATCH(TRIM(CLEAN(E82)),account!$A:$A,0)),"Not Found")) -> 882.12 | K82: =IF(E82="","No account",IFERROR(INDEX(account!$E:$E,MATCH(TRIM(CLEAN(E82)),account!$A:$A,0)),"Not Found")) -> 2769 | L82: Won | M82: 42697 | N82: 42797 | O82: 5790 | P82: =IF(OR(M82="",N82=""),"N/A",IF(N82<M82,"ERROR","OK")) -> OK | Q82: =IF(Table1[[#This Row],[deal_stage]]="Won",1,0) -> 1 | R82: =IF(Table1[[#This Row],[deal_stage]] ="Lost",1,0) -> 0
A83: N0ONCYVZ | B83: Donn Cantrell | C83: =VLOOKUP(Table1[[#This Row],[sales_agent]],'sales team'!A:C,2,FALSE) -> Rocco Neubert | D83: =IF(E83="","No account",IFERROR(INDEX(account!$B:$B,MATCH(TRIM(CLEAN(E83)),account!$A:$A,0)),"Not Found")) -> retail | E83: =TRIM(CLEAN(I83)) -> Kinnamplus | F83: =VLOOKUP(Table1[[#This Row],[sales_agent]],'sales team'!A:C,3,FALSE) -> East | G83: =IF(E83="","No account",IFERROR(INDEX(account!$F:$F,MATCH(TRIM(CLEAN(E83)),account!$A:$A,0)),"Not Found")) -> United States | H83: MG Special | I83: Kinnamplus | J83: =IF(E83="","No account",IFERROR(INDEX(account!$D:$D,MATCH(TRIM(CLEAN(E83)),account!$A:$A,0)),"Not Found")) -> 702.72 | K83: =IF(E83="","No account",IFERROR(INDEX(account!$E:$E,MATCH(TRIM(CLEAN(E83)),account!$A:$A,0)),"Not Found")) -> 1831 | L83: Lost | M83: 42697 | N83: 42824 | O83: 0 | P83: =IF(OR(M83="",N83=""),"N/A",IF(N83<M83,"ERROR","OK")) -> OK | Q83: =IF(Table1[[#This Row],[deal_stage]]="Won",1,0) -> 0 | R83: =IF(Table1[[#This Row],[deal_stage]] ="Lost",1,0) -> 1
A84: GYB4W2AU | B84: Elease Gluck | C84: =VLOOKUP(Table1[[#This Row],[sales_agent]],'sales team'!A:C,2,FALSE) -> Celia Rouche | D84: =IF(E84="","No account",IFERROR(INDEX(account!$B:$B,MATCH(TRIM(CLEAN(E84)),account!$A:$A,0)),"Not Found")) -> No account | E84: =TRIM(CLEAN(I84)) | F84: =VLOOKUP(Table1[[#This Row],[sales_agent]],'sales team'!A:C,3,FALSE) -> West | G84: =IF(E84="","No account",IFERROR(INDEX(account!$F:$F,MATCH(TRIM(CLEAN(E84)),account!$A:$A,0)),"Not Found")) -> No account | H84: MG Advanced | J84: =IF(E84="","No account",IFERROR(INDEX(account!$D:$D,MATCH(TRIM(CLEAN(E84)),account!$A:$A,0)),"Not Found")) -> No account | K84: =IF(E84="","No account",IFERROR(INDEX(account!$E:$E,MATCH(TRIM(CLEAN(E84)),account!$A:$A,0)),"Not Found")) -> No account | L84: Engaging | M84: 42697 | P84: =IF(OR(M84="",N84=""),"N/A",IF(N84<M84,"ERROR","OK")) -> N/A | Q84: =IF(Table1[[#This Row],[deal_stage]]="Won",1,0) -> 0 | R84: =IF(Table1[[#This Row],[deal_stage]] ="Lost",1,0) -> 0
A85: 513DPFX5 | B85: Gladys Colclough | C85: =VLOOKUP(Table1[[#This Row],[sales_agent]],'sales team'!A:C,2,FALSE) -> Melvin Marxen | D85: =IF(E85="","No account",IFERROR(INDEX(account!$B:$B,MATCH(TRIM(CLEAN(E85)),account!$A:$A,0)),"Not Found")) -> software | E85: =TRIM(CLEAN(I85)) -> Codehow | F85: =VLOOKUP(Table1[[#This Row],[sales_agent]],'sales team'!A:C,3,FALSE) -> Central | G85: =IF(E85="","No account",IFERROR(INDEX(account!$F:$F,MATCH(TRIM(CLEAN(E85)),account!$A:$A,0)),"Not Found")) -> United States | H85: GTXPro | I85: Codehow | J85: =IF(E85="","No account",IFERROR(INDEX(account!$D:$D,MATCH(TRIM(CLEAN(E85)),account!$A:$A,0)),"Not Found")) -> 2714.9 | K85: =IF(E85="","No account",IFERROR(INDEX(account!$E:$E,MATCH(TRIM(CLEAN(E85)),account!$A:$A,0)),"Not Found")) -> 2641 | L85: Won | M85: 42697 | N85: 42797 | O85: 4438 | P85: =IF(OR(M85="",N85=""),"N/A",IF(N85<M85,"ERROR","OK")) -> OK | Q85: =IF(Table1[[#This Row],[deal_stage]]="Won",1,0) -> 1 | R85: =IF(Table1[[#This Row],[deal_stage]] ="Lost",1,0) -> 0
A86: RU023K5W | B86: Gladys Colclough | C86: =VLOOKUP(Table1[[#This Row],[sales_agent]],'sales team'!A:C,2,FALSE) -> Melvin Marxen | D86: =IF(E86="","No account",IFERROR(INDEX(account!$B:$B,MATCH(TRIM(CLEAN(E86)),account!$A:$A,0)),"Not Found")) -> finance | E86: =TRIM(CLEAN(I86)) -> Finhigh | F86: =VLOOKUP(Table1[[#This Row],[sales_agent]],'sales team'!A:C,3,FALSE) -> Central | G86: =IF(E86="","No account",IFERROR(INDEX(account!$F:$F,MATCH(TRIM(CLEAN(E86)),account!$A:$A,0)),"Not Found")) -> United States | H86: MG Advanced | I86: Finhigh | J86: =IF(E86="","No account",IFERROR(INDEX(account!$D:$D,MATCH(TRIM(CLEAN(E86)),account!$A:$A,0)),"Not Found")) -> 1102.43 | K86: =IF(E86="","No account",IFERROR(INDEX(account!$E:$E,MATCH(TRIM(CLEAN(E86)),account!$A:$A,0)),"Not Found")) -> 1759 | L86: Won | M86: 42697 | N86: 42811 | O86: 2972 | P86: =IF(OR(M86="",N86=""),"N/A",IF(N86<M86,"ERROR","OK")) -> OK | Q86: =IF(Table1[[#This Row],[deal_stage]]="Won",1,0) -> 1 | R86: =IF(Table1[[#This Row],[deal_stage]] ="Lost",1,0) -> 0
A87: VDIU10RV | B87: Markita Hansen | C87: =VLOOKUP(Table1[[#This Row],[sales_agent]],'sales team'!A:C,2,FALSE) -> Celia Rouche | D87: =IF(E87="","No account",IFERROR(INDEX(account!$B:$B,MATCH(TRIM(CLEAN(E87)),account!$A:$A,0)),"Not Found")) -> medical | E87: =TRIM(CLEAN(I87)) -> Lexiqvolax | F87: =VLOOKUP(Table1[[#This Row],[sales_agent]],'sales team'!A:C,3,FALSE) -> West | G87: =IF(E87="","No account",IFERROR(INDEX(account!$F:$F,MATCH(TRIM(CLEAN(E87)),account!$A:$A,0)),"Not Found")) -> United States | H87: MG Special | I87: Lexiqvolax | J87: =IF(E87="","No account",IFERROR(INDEX(account!$D:$D,MATCH(TRIM(CLEAN(E87)),account!$A:$A,0)),"Not Found")) -> 1618.89 | K87: =IF(E87="","No account",IFERROR(INDEX(account!$E:$E,MATCH(TRIM(CLEAN(E87)),account!$A:$A,0)),"Not Found")) -> 3889 | L87: Engaging | M87: 42697 | P87: =IF(OR(M87="",N87=""),"N/A",IF(N87<M87,"ERROR","OK")) -> N/A | Q87: =IF(Table1[[#This Row],[deal_stage]]="Won",1,0) -> 0 | R87: =IF(Table1[[#This Row],[deal_stage]] ="Lost",1,0) -> 0
A88: BZCBQ514 | B88: Markita Hansen | C88: =VLOOKUP(Table1[[#This Row],[sales_agent]],'sales team'!A:C,2,FALSE) -> Celia Rouche | D88: =IF(E88="","No account",IFERROR(INDEX(account!$B:$B,MATCH(TRIM(CLEAN(E88)),account!$A:$A,0)),"Not Found")) -> employment | E88: =TRIM(CLEAN(I88)) -> Y-corporation | F88: =VLOOKUP(Table1[[#This Row],[sales_agent]],'sales team'!A:C,3,FALSE) -> West | G88: =IF(E88="","No account",IFERROR(INDEX(account!$F:$F,MATCH(TRIM(CLEAN(E88)),account!$A:$A,0)),"Not Found")) -> United States | H88: GTX Basic | I88: Y-corporation | J88: =IF(E88="","No account",IFERROR(INDEX(account!$D:$D,MATCH(TRIM(CLEAN(E88)),account!$A:$A,0)),"Not Found")) -> 2871.35 | K88: =IF(E88="","No account",IFERROR(INDEX(account!$E:$E,MATCH(TRIM(CLEAN(E88)),account!$A:$A,0)),"Not Found")) -> 9561 | L88: Won | M88: 42697 | N88: 42795 | O88: 523 | P88: =IF(OR(M88="",N88=""),"N/A",IF(N88<M88,"ERROR","OK")) -> OK | Q88: =IF(Table1[[#This Row],[deal_stage]]="Won",1,0) -> 1 | R88: =IF(Table1[[#This Row],[deal_stage]] ="Lost",1,0) -> 0
A89: HEE6P0QH | B89: Anna Snelling | C89: =VLOOKUP(Table1[[#This Row],[sales_agent]],'sales team'!A:C,2,FALSE) -> Dustin Brinkmann | D89: =IF(E89="","No account",IFERROR(INDEX(account!$B:$B,MATCH(TRIM(CLEAN(E89)),account!$A:$A,0)),"Not Found")) -> employment | E89: =TRIM(CLEAN(I89)) -> Statholdings | F89: =VLOOKUP(Table1[[#This Row],[sales_agent]],'sales team'!A:C,3,FALSE) -> Central | G89: =IF(E89="","No account",IFERROR(INDEX(account!$F:$F,MATCH(TRIM(CLEAN(E89)),account!$A:$A,0)),"Not Found")) -> United States | H89: MG Advanced | I89: Statholdings | J89: =IF(E89="","No account",IFERROR(INDEX(account!$D:$D,MATCH(TRIM(CLEAN(E89)),account!$A:$A,0)),"Not Found")) -> 291.27 | K89: =IF(E89="","No account",IFERROR(INDEX(account!$E:$E,MATCH(TRIM(CLEAN(E89)),account!$A:$A,0)),"Not Found")) -> 586 | L89: Won | M89: 42698 | N89: 42819 | O89: 3647 | P89: =IF(OR(M89="",N89=""),"N/A",IF(N89<M89,"ERROR","OK")) -> OK | Q89: =IF(Table1[[#This Row],[deal_stage]]="Won",1,0) -> 1 | R89: =IF(Table1[[#This Row],[deal_stage]] ="Lost",1,0) -> 0
A90: L8CHRJ2B | B90: Cassey Cress | C90: =VLOOKUP(Table1[[#This Row],[sales_agent]],'sales team'!A:C,2,FALSE) -> Rocco Neubert | D90: =IF(E90="","No account",IFERROR(INDEX(account!$B:$B,MATCH(TRIM(CLEAN(E90)),account!$A:$A,0)),"Not Found")) -> finance | E90: =TRIM(CLEAN(I90)) -> Umbrella Corporation | F90: =VLOOKUP(Table1[[#This Row],[sales_agent]],'sales team'!A:C,3,FALSE) -> East | G90: =IF(E90="","No account",IFERROR(INDEX(account!$F:$F,MATCH(TRIM(CLEAN(E90)),account!$A:$A,0)),"Not Found")) -> United States | H90: MG Advanced | I90: Umbrella Corporation | J90: =IF(E90="","No account",IFERROR(INDEX(account!$D:$D,MATCH(TRIM(CLEAN(E90)),account!$A:$A,0)),"Not Found")) -> 2022.14 | K90: =IF(E90="","No account",IFERROR(INDEX(account!$E:$E,MATCH(TRIM(CLEAN(E90)),account!$A:$A,0)),"Not Found")) -> 5113 | L90: Won | M90: 42698 | N90: 42795 | O90: 4200 | P90: =IF(OR(M90="",N90=""),"N/A",IF(N90<M90,"ERROR","OK")) -> OK | Q90: =IF(Table1[[#This Row],[deal_stage]]="Won",1,0) -> 1 | R90: =IF(Table1[[#This Row],[deal_stage]] ="Lost",1,0) -> 0
A91: 579LZ3F9 | B91: Daniell Hammack | C91: =VLOOKUP(Table1[[#This Row],[sales_agent]],'sales team'!A:C,2,FALSE) -> Rocco Neubert | D91: =IF(E91="","No account",IFERROR(INDEX(account!$B:$B,MATCH(TRIM(CLEAN(E91)),account!$A:$A,0)),"Not Found")) -> retail | E91: =TRIM(CLEAN(I91)) -> J-Texon | F91: =VLOOKUP(Table1[[#This Row],[sales_agent]],'sales team'!A:C,3,FALSE) -> East | G91: =IF(E91="","No account",IFERROR(INDEX(account!$F:$F,MATCH(TRIM(CLEAN(E91)),account!$A:$A,0)),"Not Found")) -> United States | H91: GTX Plus Basic | I91: J-Texon | J91: =IF(E91="","No account",IFERROR(INDEX(account!$D:$D,MATCH(TRIM(CLEAN(E91)),account!$A:$A,0)),"Not Found")) -> 1388.67 | K91: =IF(E91="","No account",IFERROR(INDEX(account!$E:$E,MATCH(TRIM(CLEAN(E91)),account!$A:$A,0)),"Not Found")) -> 3583 | L91: Engaging | M91: 42698 | P91: =IF(OR(M91="",N91=""),"N/A",IF(N91<M91,"ERROR","OK")) -> N/A | Q91: =IF(Table1[[#This Row],[deal_stage]]="Won",1,0) -> 0 | R91: =IF(Table1[[#This Row],[deal_stage]] ="Lost",1,0) -> 0
A92: SU8JNMP4 | B92: Kami Bicknell | C92: =VLOOKUP(Table1[[#This Row],[sales_agent]],'sales team'!A:C,2,FALSE) -> Summer Sewald | D92: =IF(E92="","No account",IFERROR(INDEX(account!$B:$B,MATCH(TRIM(CLEAN(E92)),account!$A:$A,0)),"Not Found")) -> software | E92: =TRIM(CLEAN(I92)) -> Bubba Gump | F92: =VLOOKUP(Table1[[#This Row],[sales_agent]],'sales team'!A:C,3,FALSE) -> West | G92: =IF(E92="","No account",IFERROR(INDEX(account!$F:$F,MATCH(TRIM(CLEAN(E92)),account!$A:$A,0)),"Not Found")) -> United States | H92: GTX Plus Basic | I92: Bubba Gump | J92: =IF(E92="","No account",IFERROR(INDEX(account!$D:$D,MATCH(TRIM(CLEAN(E92)),account!$A:$A,0)),"Not Found")) -> 987.39 | K92: =IF(E92="","No account",IFERROR(INDEX(account!$E:$E,MATCH(TRIM(CLEAN(E92)),account!$A:$A,0)),"Not Found")) -> 2253 | L92: Engaging | M92: 42698 | P92: =IF(OR(M92="",N92=""),"N/A",IF(N92<M92,"ERROR","OK")) -> N/A | Q92: =IF(Table1[[#This Row],[deal_stage]]="Won",1,0) -> 0 | R92: =IF(Table1[[#This Row],[deal_stage]] ="Lost",1,0) -> 0
A93: V2X2KMUR | B93: Kami Bicknell | C93: =VLOOKUP(Table1[[#This Row],[sales_agent]],'sales team'!A:C,2,FALSE) -> Summer Sewald | D93: =IF(E93="","No account",IFERROR(INDEX(account!$B:$B,MATCH(TRIM(CLEAN(E93)),account!$A:$A,0)),"Not Found")) -> telecommunications | E93: =TRIM(CLEAN(I93)) -> Faxquote | F93: =VLOOKUP(Table1[[#This Row],[sales_agent]],'sales team'!A:C,3,FALSE) -> West | G93: =IF(E93="","No account",IFERROR(INDEX(account!$F:$F,MATCH(TRIM(CLEAN(E93)),account!$A:$A,0)),"Not Found")) -> United States | H93: GTX Plus Basic | I93: Faxquote | J93: =IF(E93="","No account",IFERROR(INDEX(account!$D:$D,MATCH(TRIM(CLEAN(E93)),account!$A:$A,0)),"Not Found")) -> 1825.82 | K93: =IF(E93="","No account",IFERROR(INDEX(account!$E:$E,MATCH(TRIM(CLEAN(E93)),account!$A:$A,0)),"Not Found")) -> 5595 | L93: Won | M93: 42698 | N93: 42822 | O93: 1059 | P93: =IF(OR(M93="",N93=""),"N/A",IF(N93<M93,"ERROR","OK")) -> OK | Q93: =IF(Table1[[#This Row],[deal_stage]]="Won",1,0) -> 1 | R93: =IF(Table1[[#This Row],[deal_stage]] ="Lost",1,0) -> 0
A94: AJIPJP75 | B94: Marty Freudenburg | C94: =VLOOKUP(Table1[[#This Row],[sales_agent]],'sales team'!A:C,2,FALSE) -> Melvin Marxen | D94: =IF(E94="","No account",IFERROR(INDEX(account!$B:$B,MATCH(TRIM(CLEAN(E94)),account!$A:$A,0)),"Not Found")) -> software | E94: =TRIM(CLEAN(I94)) -> Codehow | F94: =VLOOKUP(Table1[[#This Row],[sales_agent]],'sales team'!A:C,3,FALSE) -> Central | G94: =IF(E94="","No account",IFERROR(INDEX(account!$F:$F,MATCH(TRIM(CLEAN(E94)),account!$A:$A,0)),"Not Found")) -> United States | H94: GTX Plus Basic | I94: Codehow | J94: =IF(E94="","No account",IFERROR(INDEX(account!$D:$D,MATCH(TRIM(CLEAN(E94)),account!$A:$A,0)),"Not Found")) -> 2714.9 | K94: =IF(E94="","No account",IFERROR(INDEX(account!$E:$E,MATCH(TRIM(CLEAN(E94)),account!$A:$A,0)),"Not Found")) -> 2641 | L94: Lost | M94: 42698 | N94: 42799 | O94: 0 | P94: =IF(OR(M94="",N94=""),"N/A",IF(N94<M94,"ERROR","OK")) -> OK | Q94: =IF(Table1[[#This Row],[deal_stage]]="Won",1,0) -> 0 | R94: =IF(Table1[[#This Row],[deal_stage]] ="Lost",1,0) -> 1
A95: NYVA2G6U | B95: Versie Hillebrand | C95: =VLOOKUP(Table1[[#This Row],[sales_agent]],'sales team'!A:C,2,FALSE) -> Dustin Brinkmann | D95: =IF(E95="","No account",IFERROR(INDEX(account!$B:$B,MATCH(TRIM(CLEAN(E95)),account!$A:$A,0)),"Not Found")) -> software | E95: =TRIM(CLEAN(I95)) -> Dontechi | F95: =VLOOKUP(Table1[[#This Row],[sales_agent]],'sales team'!A:C,3,FALSE) -> Central | G95: =IF(E95="","No account",IFERROR(INDEX(account!$F:$F,MATCH(TRIM(CLEAN(E95)),account!$A:$A,0)),"Not Found")) -> United States | H95: MG Special | I95: Dontechi | J95: =IF(E95="","No account",IFERROR(INDEX(account!$D:$D,MATCH(TRIM(CLEAN(E95)),account!$A:$A,0)),"Not Found")) -> 4618 | K95: =IF(E95="","No account",IFERROR(INDEX(account!$E:$E,MATCH(TRIM(CLEAN(E95)),account!$A:$A,0)),"Not Found")) -> 10083 | L95: Won | M95: 42698 | N95: 42796 | O95: 57 | P95: =IF(OR(M95="",N95=""),"N/A",IF(N95<M95,"ERROR","OK")) -> OK | Q95: =IF(Table1[[#This Row],[deal_stage]]="Won",1,0) -> 1 | R95: =IF(Table1[[#This Row],[deal_stage]] ="Lost",1,0) -> 0
A96: FF45BXTL | B96: Vicki Laflamme | C96: =VLOOKUP(Table1[[#This Row],[sales_agent]],'sales team'!A:C,2,FALSE) -> Celia Rouche | D96: =IF(E96="","No account",IFERROR(INDEX(account!$B:$B,MATCH(TRIM(CLEAN(E96)),account!$A:$A,0)),"Not Found")) -> technolgy | E96: =TRIM(CLEAN(I96)) -> Konex | F96: =VLOOKUP(Table1[[#This Row],[sales_agent]],'sales team'!A:C,3,FALSE) -> West | G96: =IF(E96="","No account",IFERROR(INDEX(account!$F:$F,MATCH(TRIM(CLEAN(E96)),account!$A:$A,0)),"Not Found")) -> United States | H96: MG Advanced | I96: Konex | J96: =IF(E96="","No account",IFERROR(INDEX(account!$D:$D,MATCH(TRIM(CLEAN(E96)),account!$A:$A,0)),"Not Found")) -> 7708.38 | K96: =IF(E96="","No account",IFERROR(INDEX(account!$E:$E,MATCH(TRIM(CLEAN(E96)),account!$A:$A,0)),"Not Found")) -> 13756 | L96: Won | M96: 42698 | N96: 42821 | O96: 3671 | P96: =IF(OR(M96="",N96=""),"N/A",IF(N96<M96,"ERROR","OK")) -> OK | Q96: =IF(Table1[[#This Row],[deal_stage]]="Won",1,0) -> 1 | R96: =IF(Table1[[#This Row],[deal_stage]] ="Lost",1,0) -> 0
A97: TTA9LYBS | B97: Anna Snelling | C97: =VLOOKUP(Table1[[#This Row],[sales_agent]],'sales team'!A:C,2,FALSE) -> Dustin Brinkmann | D97: =IF(E97="","No account",IFERROR(INDEX(account!$B:$B,MATCH(TRIM(CLEAN(E97)),account!$A:$A,0)),"Not Found")) -> telecommunications | E97: =TRIM(CLEAN(I97)) -> Treequote | F97: =VLOOKUP(Table1[[#This Row],[sales_agent]],'sales team'!A:C,3,FALSE) -> Central | G97: =IF(E97="","No account",IFERROR(INDEX(account!$F:$F,MATCH(TRIM(CLEAN(E97)),account!$A:$A,0)),"Not Found")) -> United States | H97: MG Special | I97: Treequote | J97: =IF(E97="","No account",IFERROR(INDEX(account!$D:$D,MATCH(TRIM(CLEAN(E97)),account!$A:$A,0)),"Not Found")) -> 5266.09 | K97: =IF(E97="","No account",IFERROR(INDEX(account!$E:$E,MATCH(TRIM(CLEAN(E97)),account!$A:$A,0)),"Not Found")) -> 8595 | L97: Won | M97: 42699 | N97: 42795 | O97: 58 | P97: =IF(OR(M97="",N97=""),"N/A",IF(N97<M97,"ERROR","OK")) -> OK | Q97: =IF(Table1[[#This Row],[deal_stage]]="Won",1,0) -> 1 | R97: =IF(Table1[[#This Row],[deal_stage]] ="Lost",1,0) -> 0
A98: PAGZQH8L | B98: Cecily Lampkin | C98: =VLOOKUP(Table1[[#This Row],[sales_agent]],'sales team'!A:C,2,FALSE) -> Dustin Brinkmann | D98: =IF(E98="","No account",IFERROR(INDEX(account!$B:$B,MATCH(TRIM(CLEAN(E98)),account!$A:$A,0)),"Not Found")) -> telecommunications | E98: =TRIM(CLEAN(I98)) -> Treequote | F98: =VLOOKUP(Table1[[#This Row],[sales_agent]],'sales team'!A:C,3,FALSE) -> Central | G98: =IF(E98="","No account",IFERROR(INDEX(account!$F:$F,MATCH(TRIM(CLEAN(E98)),account!$A:$A,0)),"Not Found")) -> United States | H98: MG Advanced | I98: Treequote | J98: =IF(E98="","No account",IFERROR(INDEX(account!$D:$D,MATCH(TRIM(CLEAN(E98)),account!$A:$A,0)),"Not Found")) -> 5266.09 | K98: =IF(E98="","No account",IFERROR(INDEX(account!$E:$E,MATCH(TRIM(CLEAN(E98)),account!$A:$A,0)),"Not Found")) -> 8595 | L98: Won | M98: 42699 | N98: 42800 | O98: 3956 | P98: =IF(OR(M98="",N98=""),"N/A",IF(N98<M98,"ERROR","OK")) -> OK | Q98: =IF(Table1[[#This Row],[deal_stage]]="Won",1,0) -> 1 | R98: =IF(Table1[[#This Row],[deal_stage]] ="Lost",1,0) -> 0
A99: J7YF6DS7 | B99: Corliss Cosme | C99: =VLOOKUP(Table1[[#This Row],[sales_agent]],'sales team'!A:C,2,FALSE) -> Cara Losch | D99: =IF(E99="","No account",IFERROR(INDEX(account!$B:$B,MATCH(TRIM(CLEAN(E99)),account!$A:$A,0)),"Not Found")) -> medical | E99: =TRIM(CLEAN(I99)) -> Betasoloin | F99: =VLOOKUP(Table1[[#This Row],[sales_agent]],'sales team'!A:C,3,FALSE) -> East | G99: =IF(E99="","No account",IFERROR(INDEX(account!$F:$F,MATCH(TRIM(CLEAN(E99)),account!$A:$A,0)),"Not Found")) -> United States | H99: GTX Plus Pro | I99: Betasoloin | J99: =IF(E99="","No account",IFERROR(INDEX(account!$D:$D,MATCH(TRIM(CLEAN(E99)),account!$A:$A,0)),"Not Found")) -> 251.41 | K99: =IF(E99="","No account",IFERROR(INDEX(account!$E:$E,MATCH(TRIM(CLEAN(E99)),account!$A:$A,0)),"Not Found")) -> 495 | L99: Won | M99: 42699 | N99: 42795 | O99: 5964 | P99: =IF(OR(M99="",N99=""),"N/A",IF(N99<M99,"ERROR","OK")) -> OK | Q99: =IF(Table1[[#This Row],[deal_stage]]="Won",1,0) -> 1 | R99: =IF(Table1[[#This Row],[deal_stage]] ="Lost",1,0) -> 0
A100: S5IXY4Z9 | B100: Corliss Cosme | C100: =VLOOKUP(Table1[[#This Row],[sales_agent]],'sales team'!A:C,2,FALSE) -> Cara Losch | D100: =IF(E100="","No account",IFERROR(INDEX(account!$B:$B,MATCH(TRIM(CLEAN(E100)),account!$A:$A,0)),"Not Found")) -> medical | E100: =TRIM(CLEAN(I100)) -> Betasoloin | F100: =VLOOKUP(Table1[[#This Row],[sales_agent]],'sales team'!A:C,3,FALSE) -> East | G100: =IF(E100="","No account",IFERROR(INDEX(account!$F:$F,MATCH(TRIM(CLEAN(E100)),account!$A:$A,0)),"Not Found")) -> United States | H100: GTXPro | I100: Betasoloin | J100: =IF(E100="","No account",IFERROR(INDEX(account!$D:$D,MATCH(TRIM(CLEAN(E100)),account!$A:$A,0)),"Not Found")) -> 251.41 | K100: =IF(E100="","No account",IFERROR(INDEX(account!$E:$E,MATCH(TRIM(CLEAN(E100)),account!$A:$A,0)),"Not Found")) -> 495 | L100: Won | M100: 42699 | N100: 42800 | O100: 4570 | P100: =IF(OR(M100="",N100=""),"N/A",IF(N100<M100,"ERROR","OK")) -> OK | Q100: =IF(Table1[[#This Row],[deal_stage]]="Won",1,0) -> 1 | R100: =IF(Table1[[#This Row],[deal_stage]] ="Lost",1,0) -> 0
A101: JQBJMETQ | B101: Darcel Schlecht | C101: =VLOOKUP(Table1[[#This Row],[sales_agent]],'sales team'!A:C,2,FALSE) -> Melvin Marxen | D101: =IF(E101="","No account",IFERROR(INDEX(account!$B:$B,MATCH(TRIM(CLEAN(E101)),account!$A:$A,0)),"Not Found")) -> entertainment | E101: =TRIM(CLEAN(I101)) -> Domzoom | F101: =VLOOKUP(Table1[[#This Row],[sales_agent]],'sales team'!A:C,3,FALSE) -> Central | G101: =IF(E101="","No account",IFERROR(INDEX(account!$F:$F,MATCH(TRIM(CLEAN(E101)),account!$A:$A,0)),"Not Found")) -> United States | H101: MG Special | I101: Domzoom | J101: =IF(E101="","No account",IFERROR(INDEX(account!$D:$D,MATCH(TRIM(CLEAN(E101)),account!$A:$A,0)),"Not Found")) -> 217.87 | K101: =IF(E101="","No account",IFERROR(INDEX(account!$E:$E,MATCH(TRIM(CLEAN(E101)),account!$A:$A,0)),"Not Found")) -> 551 | L101: Won | M101: 42699 | N101: 42821 | O101: 49 | P101: =IF(OR(M101="",N101=""),"N/A",IF(N101<M101,"ERROR","OK")) -> OK | Q101: =IF(Table1[[#This Row],[deal_stage]]="Won",1,0) -> 1 | R101: =IF(Table1[[#This Row],[deal_stage]] ="Lost",1,0) -> 0
A102: 0LVWSWEW | B102: Violet Mclelland | C102: =VLOOKUP(Table1[[#This Row],[sales_agent]],'sales team'!A:C,2,FALSE) -> Cara Losch | D102: =IF(E102="","No account",IFERROR(INDEX(account!$B:$B,MATCH(TRIM(CLEAN(E102)),account!$A:$A,0)),"Not Found")) -> technolgy | E102: =TRIM(CLEAN(I102)) -> Donquadtech | F102: =VLOOKUP(Table1[[#This Row],[sales_agent]],'sales team'!A:C,3,FALSE) -> East | G102: =IF(E102="","No account",IFERROR(INDEX(account!$F:$F,MATCH(TRIM(CLEAN(E102)),account!$A:$A,0)),"Not Found")) -> United States | H102: MG Special | I102: Donquadtech | J102: =IF(E102="","No account",IFERROR(INDEX(account!$D:$D,MATCH(TRIM(CLEAN(E102)),account!$A:$A,0)),"Not Found")) -> 1712.68 | K102: =IF(E102="","No account",IFERROR(INDEX(account!$E:$E,MATCH(TRIM(CLEAN(E102)),account!$A:$A,0)),"Not Found")) -> 3194 | L102: Won | M102: 42699 | N102: 42800 | O102: 65 | P102: =IF(OR(M102="",N102=""),"N/A",IF(N102<M102,"ERROR","OK")) -> OK | Q102: =IF(Table1[[#This Row],[deal_stage]]="Won",1,0) -> 1 | R102: =IF(Table1[[#This Row],[deal_stage]] ="Lost",1,0) -> 0
A103: K53BC1T9 | B103: Anna Snelling | C103: =VLOOKUP(Table1[[#This Row],[sales_agent]],'sales team'!A:C,2,FALSE) -> Dustin Brinkmann | D103: =IF(E103="","No account",IFERROR(INDEX(account!$B:$B,MATCH(TRIM(CLEAN(E103)),account!$A:$A,0)),"Not Found")) -> entertainment | E103: =TRIM(CLEAN(I103)) -> Domzoom | F103: =VLOOKUP(Table1[[#This Row],[sales_agent]],'sales team'!A:C,3,FALSE) -> Central | G103: =IF(E103="","No account",IFERROR(INDEX(account!$F:$F,MATCH(TRIM(CLEAN(E103)),account!$A:$A,0)),"Not Found")) -> United States | H103: MG Special | I103: Domzoom | J103: =IF(E103="","No account",IFERROR(INDEX(account!$D:$D,MATCH(TRIM(CLEAN(E103)),account!$A:$A,0)),"Not Found")) -> 217.87 | K103: =IF(E103="","No account",IFERROR(INDEX(account!$E:$E,MATCH(TRIM(CLEAN(E103)),account!$A:$A,0)),"Not Found")) -> 551 | L103: Lost | M103: 42700 | N103: 42821 | O103: 0 | P103: =IF(OR(M103="",N103=""),"N/A",IF(N103<M103,"ERROR","OK")) -> OK | Q103: =IF(Table1[[#This Row],[deal_stage]]="Won",1,0) -> 0 | R103: =IF(Table1[[#This Row],[deal_stage]] ="Lost",1,0) -> 1
A104: D40N5I9Y | B104: Darcel Schlecht | C104: =VLOOKUP(Table1[[#This Row],[sales_agent]],'sales team'!A:C,2,FALSE) -> Melvin Marxen | D104: =IF(E104="","No account",IFERROR(INDEX(account!$B:$B,MATCH(TRIM(CLEAN(E104)),account!$A:$A,0)),"Not Found")) -> finance | E104: =TRIM(CLEAN(I104)) -> Finhigh | F104: =VLOOKUP(Table1[[#This Row],[sales_agent]],'sales team'!A:C,3,FALSE) -> Central | G104: =IF(E104="","No account",IFERROR(INDEX(account!$F:$F,MATCH(TRIM(CLEAN(E104)),account!$A:$A,0)),"Not Found")) -> United States | H104: GTXPro | I104: Finhigh | J104: =IF(E104="","No account",IFERROR(INDEX(account!$D:$D,MATCH(TRIM(CLEAN(E104)),account!$A:$A,0)),"Not Found")) -> 1102.43 | K104: =IF(E104="","No account",IFERROR(INDEX(account!$E:$E,MATCH(TRIM(CLEAN(E104)),account!$A:$A,0)),"Not Found")) -> 1759 | L104: Won | M104: 42700 | N104: 42802 | O104: 4739 | P104: =IF(OR(M104="",N104=""),"N/A",IF(N104<M104,"ERROR","OK")) -> OK | Q104: =IF(Table1[[#This Row],[deal_stage]]="Won",1,0) -> 1 | R104: =IF(Table1[[#This Row],[deal_stage]] ="Lost",1,0) -> 0
... A108: UK0LEZRJ | B108: Kary Hendrixson | C108: =VLOOKUP(Table1[[#This Row],[sales_agent]],'sales team'!A:C,2,FALSE) -> Summer Sewald | D108: =IF(E108="","No account",IFERROR(INDEX(account!$B:$B,MATCH(TRIM(CLEAN(E108)),account!$A:$A,0)),"Not Found")) -> medical | E108: =TRIM(CLEAN(I108)) -> Condax | F108: =VLOOKUP(Table1[[#This Row],[sales_agent]],'sales team'!A:C,3,FALSE) -> West | G108: =IF(E108="","No account",IFERROR(INDEX(account!$F:$F,MATCH(TRIM(CLEAN(E108)),account!$A:$A,0)),"Not Found")) -> United States | H108: GTX Basic | I108: Condax | J108: =IF(E108="","No account",IFERROR(INDEX(account!$D:$D,MATCH(TRIM(CLEAN(E108)),account!$A:$A,0)),"Not Found")) -> 4.54 | K108: =IF(E108="","No account",IFERROR(INDEX(account!$E:$E,MATCH(TRIM(CLEAN(E108)),account!$A:$A,0)),"Not Found")) -> 9 | L108: Won | M108: 42701 | N108: 42797 | O108: 532 | P108: =IF(OR(M108="",N108=""),"N/A",IF(N108<M108,"ERROR","OK")) -> OK | Q108: =IF(Table1[[#This Row],[deal_stage]]="Won",1,0) -> 1 | R108: =IF(Table1[[#This Row],[deal_stage]] ="Lost",1,0) -> 0
A109: PFFHM7HR | B109: Markita Hansen | C109: =VLOOKUP(Table1[[#This Row],[sales_agent]],'sales team'!A:C,2,FALSE) -> Celia Rouche | D109: =IF(E109="","No account",IFERROR(INDEX(account!$B:$B,MATCH(TRIM(CLEAN(E109)),account!$A:$A,0)),"Not Found")) -> finance | E109: =TRIM(CLEAN(I109)) -> Opentech | F109: =VLOOKUP(Table1[[#This Row],[sales_agent]],'sales team'!A:C,3,FALSE) -> West | G109: =IF(E109="","No account",IFERROR(INDEX(account!$F:$F,MATCH(TRIM(CLEAN(E109)),account!$A:$A,0)),"Not Found")) -> United States | H109: MG Advanced | I109: Opentech | J109: =IF(E109="","No account",IFERROR(INDEX(account!$D:$D,MATCH(TRIM(CLEAN(E109)),account!$A:$A,0)),"Not Found")) -> 355.23 | K109: =IF(E109="","No account",IFERROR(INDEX(account!$E:$E,MATCH(TRIM(CLEAN(E109)),account!$A:$A,0)),"Not Found")) -> 853 | L109: Engaging | M109: 42701 | P109: =IF(OR(M109="",N109=""),"N/A",IF(N109<M109,"ERROR","OK")) -> N/A | Q109: =IF(Table1[[#This Row],[deal_stage]]="Won",1,0) -> 0 | R109: =IF(Table1[[#This Row],[deal_stage]] ="Lost",1,0) -> 0
...

Sheet account
A1: account | B1: sector | C1: year_established | D1: revenue | E1: employees | F1: office_location | G1: subsidiary_of
A2: Acme Corporation | B2: technolgy | C2: 1996 | D2: 1100.04 | E2: 2822 | F2: United States
A3: Betasoloin | B3: medical | C3: 1999 | D3: 251.41 | E3: 495 | F3: United States
A4: Betatech | B4: medical | C4: 1986 | D4: 647.18 | E4: 1185 | F4: Kenya
A5: Bioholding | B5: medical | C5: 2012 | D5: 587.34 | E5: 1356 | F5: Philipines | I5: =TRIM(CLEAN(A2:A86)) -> Bioholding
A6: Bioplex | B6: medical | C6: 1991 | D6: 326.82 | E6: 1016 | F6: United States
A7: Blackzim | B7: retail | C7: 2009 | D7: 497.11 | E7: 1588 | F7: United States
A8: Bluth Company | B8: technolgy | C8: 1993 | D8: 1242.32 | E8: 3027 | F8: United States | G8: Acme Corporation
A9: Bubba Gump | B9: software | C9: 2002 | D9: 987.39 | E9: 2253 | F9: United States
A10: Cancity | B10: retail | C10: 2001 | D10: 718.62 | E10: 2448 | F10: United States
A11: Cheers | B11: entertainment | C11: 1993 | D11: 4269.9 | E11: 6472 | F11: United States | G11: Massive Dynamic
A12: Codehow | B12: software | C12: 1998 | D12: 2714.9 | E12: 2641 | F12: United States | G12: Acme Corporation
A13: Condax | B13: medical | C13: 2017 | D13: 4.54 | E13: 9 | F13: United States
A14: Conecom | B14: technolgy | C14: 2005 | D14: 1520.66 | E14: 1806 | F14: United States
A15: Dalttechnology | B15: software | C15: 2013 | D15: 98.79 | E15: 96 | F15: United States | G15: Bubba Gump
A16: dambase | B16: marketing | C16: 1995 | D16: 2173.98 | E16: 2928 | F16: United States | G16: Inity
A17: Domzoom | B17: entertainment | C17: 1998 | D17: 217.87 | E17: 551 | F17: United States
A18: Doncon | B18: technolgy | C18: 2010 | D18: 587.72 | E18: 1501 | F18: United States
A19: Donquadtech | B19: technolgy | C19: 1992 | D19: 1712.68 | E19: 3194 | F19: United States | G19: Acme Corporation
A20: Dontechi | B20: software | C20: 1982 | D20: 4618 | E20: 10083 | F20: United States
A21: Donware | B21: marketing | C21: 1999 | D21: 1197.44 | E21: 2570 | F21: United States
A22: Fasehatice | B22: retail | C22: 1990 | D22: 4968.91 | E22: 7523 | F22: United States
A23: Faxquote | B23: telecommunications | C23: 1995 | D23: 1825.82 | E23: 5595 | F23: United States | G23: Sonron
A24: Finhigh | B24: finance | C24: 2006 | D24: 1102.43 | E24: 1759 | F24: United States
A25: Finjob | B25: employment | C25: 1988 | D25: 2059.9 | E25: 3644 | F25: United States
A26: Funholding | B26: finance | C26: 1991 | D26: 2819.5 | E26: 7227 | F26: United States | G26: Golddex
A27: Ganjaflex | B27: retail | C27: 1995 | D27: 5158.71 | E27: 17479 | F27: Japan
A28: Gekko & Co | B28: retail | C28: 1990 | D28: 2520.83 | E28: 3502 | F28: United States
A29: Genco Pura Olive Oil Company | B29: retail | C29: 2007 | D29: 894.33 | E29: 1635 | F29: Italy
A30: Globex Corporation | B30: technolgy | C30: 2000 | D30: 1223.72 | E30: 2497 | F30: Norway
A31: Gogozoom | B31: telecommunications | C31: 2007 | D31: 86.68 | E31: 187 | F31: United States | G31: Sonron
A32: Golddex | B32: finance | C32: 2008 | D32: 52.5 | E32: 165 | F32: United States
A33: Goodsilron | B33: marketing | C33: 2000 | D33: 2952.73 | E33: 5107 | F33: United States
A34: Green-Plus | B34: services | C34: 2003 | D34: 692.19 | E34: 1922 | F34: United States
A35: Groovestreet | B35: retail | C35: 2003 | D35: 223.8 | E35: 299 | F35: United States
A36: Hatfan | B36: services | C36: 1982 | D36: 792.46 | E36: 1299 | F36: United States
A37: Hottechi | B37: technolgy | C37: 1997 | D37: 8170.38 | E37: 16499 | F37: Korea
A38: Initech | B38: telecommunications | C38: 1994 | D38: 6395.05 | E38: 20275 | F38: United States
A39: Inity | B39: marketing | C39: 1986 | D39: 2403.58 | E39: 8801 | F39: United States
A40: Isdom | B40: medical | C40: 2002 | D40: 3178.24 | E40: 4540 | F40: United States
A41: Iselectrics | B41: technolgy | C41: 2011 | D41: 527.11 | E41: 1428 | F41: United States | G41: Acme Corporation
A42: J-Texon | B42: retail | C42: 1989 | D42: 1388.67 | E42: 3583 | F42: United States
A43: Kan-code | B43: software | C43: 1982 | D43: 11698.03 | E43: 34288 | F43: United States
A44: Kinnamplus | B44: retail | C44: 2004 | D44: 702.72 | E44: 1831 | F44: United States
A45: Konex | B45: technolgy | C45: 1980 | D45: 7708.38 | E45: 13756 | F45: United States
A46: Konmatfix | B46: marketing | C46: 1985 | D46: 375.43 | E46: 1190 | F46: United States
A47: Labdrill | B47: medical | C47: 1985 | D47: 2741.37 | E47: 9226 | F47: United States
A48: Lexiqvolax | B48: medical | C48: 2004 | D48: 1618.89 | E48: 3889 | F48: United States
A49: Massive Dynamic | B49: entertainment | C49: 1989 | D49: 665.06 | E49: 1095 | F49: United States
A50: Mathtouch | B50: marketing | C50: 1984 | D50: 3027.46 | E50: 9516 | F50: Jordan
A51: Nam-zim | B51: services | C51: 1987 | D51: 405.59 | E51: 1179 | F51: Brazil | G51: Warephase
A52: Newex | B52: services | C52: 1991 | D52: 1012.72 | E52: 3492 | F52: Germany
A53: Ontomedia | B53: employment | C53: 1997 | D53: 882.12 | E53: 2769 | F53: United States
A54: Opentech | B54: finance | C54: 1994 | D54: 355.23 | E54: 853 | F54: United States
A55: Plexzap | B55: retail | C55: 2001 | D55: 2437.85 | E55: 4874 | F55: United States
A56: Plusstrip | B56: entertainment | C56: 2002 | D56: 349.81 | E56: 315 | F56: United States
A57: Plussunin | B57: retail | C57: 2003 | D57: 1419.98 | E57: 4018 | F57: United States
A58: Rangreen | B58: technolgy | C58: 1987 | D58: 2938.67 | E58: 8775 | F58: Panama
A59: Rantouch | B59: telecommunications | C59: 1994 | D59: 1188.42 | E59: 3015 | F59: United States
A60: Ron-tech | B60: medical | C60: 1992 | D60: 3922.42 | E60: 6837 | F60: United States
A61: Rundofase | B61: technolgy | C61: 1983 | D61: 1008.06 | E61: 1238 | F61: United States
A62: Scotfind | B62: software | C62: 1996 | D62: 6354.87 | E62: 16780 | F62: United States | G62: Bubba Gump
A63: Scottech | B63: marketing | C63: 2012 | D63: 45.39 | E63: 100 | F63: United States | G63: Inity
A64: Silis | B64: medical | C64: 1994 | D64: 2818.38 | E64: 6290 | F64: United States
A65: Singletechno | B65: retail | C65: 1996 | D65: 2214.94 | E65: 5374 | F65: United States
A66: Sonron | B66: telecommunications | C66: 1999 | D66: 1699.85 | E66: 5108 | F66: United States
A67: Stanredtax | B67: finance | C67: 1987 | D67: 1698.2 | E67: 3798 | F67: United States
A68: Statholdings | B68: employment | C68: 1997 | D68: 291.27 | E68: 586 | F68: United States
A69: Streethex | B69: retail | C69: 1988 | D69: 1376.8 | E69: 1165 | F69: Belgium
A70: Sumace | B70: retail | C70: 2000 | D70: 167.89 | E70: 493 | F70: Romania
A71: Sunnamplex | B71: marketing | C71: 2008 | D71: 894.37 | E71: 1593 | F71: Poland
A72: The New York Inquirer | B72: medical | C72: 1996 | D72: 439.21 | E72: 792 | F72: United States
A73: Toughzap | B73: retail | C73: 1995 | D73: 332.43 | E73: 799 | F73: United States
A74: Treequote | B74: telecommunications | C74: 1988 | D74: 5266.09 | E74: 8595 | F74: United States | G74: Sonron
A75: Umbrella Corporation | B75: finance | C75: 1998 | D75: 2022.14 | E75: 5113 | F75: United States
A76: Vehement Capital Partners | B76: finance | C76: 1993 | D76: 646.1 | E76: 883 | F76: United States | G76: Golddex
A77: Warephase | B77: services | C77: 1997 | D77: 2041.73 | E77: 5276 | F77: United States
A78: Xx-holding | B78: finance | C78: 1993 | D78: 7537.24 | E78: 20293 | F78: United States
A79: Xx-zobam | B79: entertainment | C79: 1989 | D79: 3838.39 | E79: 8274 | F79: United States
A80: Y-corporation | B80: employment | C80: 1983 | D80: 2871.35 | E80: 9561 | F80: United States
A81: Yearin | B81: retail | C81: 2005 | D81: 2261.05 | E81: 3851 | F81: United States
A82: Zathunicon | B82: retail | C82: 2010 | D82: 71.12 | E82: 144 | F82: United States
A83: Zencorporation | B83: technolgy | C83: 2011 | D83: 40.79 | E83: 142 | F83: China
A84: Zoomit | B84: entertainment | C84: 1992 | D84: 324.19 | E84: 978 | F84: United States
A85: Zotware | B85: software | C85: 1979 | D85: 4478.47 | E85: 13809 | F85: United States
A86: Zumgoity | B86: medical | C86: 1984 | D86: 441.08 | E86: 1210 | F86: United States

Sheet dictionary
A1: Table | B1: Field | C1: Description
A2: accounts | B2: account | C2: Company name
A3: accounts | B3: sector | C3: Industry
A4: accounts | B4: year_established | C4: Year Established
A5: accounts | B5: revenue | C5: Annual revenue (in millions of USD)
A6: accounts | B6: employees | C6: Number of employees
A7: accounts | B7: office_location | C7: Headquarters
A8: accounts | B8: subsidiary_of | C8: Parent company
A9: products | B9: product | C9: Product name
A10: products | B10: series | C10: Product series
A11: products | B11: sales_price | C11: Suggested retail price
A12: sales_teams | B12: sales_agent | C12: Sales agent
... A22: sales_pipeline | B22: close_value | C22: Revenue from the deal

Sheet sales team
A1: sales_agent | B1: manager | C1: regional_office
A2: Anna Snelling | B2: Dustin Brinkmann | C2: Central
A3: Cecily Lampkin | B3: Dustin Brinkmann | C3: Central
A4: Versie Hillebrand | B4: Dustin Brinkmann | C4: Central
A5: Lajuana Vencill | B5: Dustin Brinkmann | C5: Central
A6: Moses Frase | B6: Dustin Brinkmann | C6: Central
A7: Jonathan Berthelot | B7: Melvin Marxen | C7: Central
A8: Marty Freudenburg | B8: Melvin Marxen | C8: Central
A9: Gladys Colclough | B9: Melvin Marxen | C9: Central
A10: Niesha Huffines | B10: Melvin Marxen | C10: Central
A11: Darcel Schlecht | B11: Melvin Marxen | C11: Central
A12: Mei-Mei Johns | B12: Melvin Marxen | C12: Central
... A36: Carl Lin | B36: Summer Sewald | C36: West
